Workbook

Sheet template
A1: Developer Evaluation Template
A3: Employee Name: | G3: Review Period: | I3: Reviewer:
A4: Position/Level: | B4: Senior Developer | I4: Date:
A6: Section | B6: Subsection | C6: Criteria | D6: Description | E6: IC Rating | F6: Role Model Rating | G6: Weight | H6: Evidence/Examples | I6: Notes
A7: =weights_editor!A3 -> ENGINEERING CRAFT | E7: =(E8*G8+E13*G13+E19*G19+E24*G24+E30*G30+E37*G37) -> 1.505 | F7: =VLOOKUP(TRIM($B$4&$A$7&B7&C7),raw_weights!A:H,7,false) -> 2.5345 | G7: =VLOOKUP(TRIM($B$4&$A$7&B7&C7),raw_weights!A:H,8,false) -> 0.6
B8: =weights_editor!B4 -> Writing Code | D8: =VLOOKUP(TRIM($B$4&$A$7&B8&C8),raw_weights!A:I,9,false) -> The ability to contribute high quality code to production environments. Is able to consistently write production-ready code across large, complex projects. | E8: =E9*G9+E10*G10+E11*G11+E12*G12 -> 1 | F8: =VLOOKUP(TRIM($B$4&$A$7&B8&C8),raw_weights!A:H,7,false) -> 2.51 | G8: =VLOOKUP(TRIM($B$4&$A$7&B8&C8),raw_weights!A:H,8,false) -> 0.35
C9: =weights_editor!C5 -> Quality | D9: =VLOOKUP(TRIM($B$4&$A$7&$B$8&C9),raw_weights!A:I,9,false) -> You're regularly trusted to lead complex and business-critical coding projects, including guiding others. | E9: 1 | F9: =VLOOKUP(TRIM($B$4&$A$7&$B$8&C9),raw_weights!A:H,7,false) -> 2.6 | G9: =VLOOKUP(TRIM($B$4&$A$7&$B$8&C9),raw_weights!A:H,8,false) -> 0.4
C10: =weights_editor!C6 -> Documentation | D10: =VLOOKUP(TRIM($B$4&$A$7&$B$8&C10),raw_weights!A:I,9,false) -> Your code is consistently self-documenting where possible. You've regularly maintained, improved and extended existing documentation unprompted. | E10: 1 | F10: =VLOOKUP(TRIM($B$4&$A$7&$B$8&C10),raw_weights!A:H,7,false) -> 2.4 | G10: =VLOOKUP(TRIM($B$4&$A$7&$B$8&C10),raw_weights!A:H,8,false) -> 0.2
C11: =weights_editor!C7 -> Language | D11: =VLOOKUP(TRIM($B$4&$A$7&$B$8&C11),raw_weights!A:I,9,false) -> You're committing quality code in any language your team needs OR you're best in class at one language. | E11: 1 | F11: =VLOOKUP(TRIM($B$4&$A$7&$B$8&C11),raw_weights!A:H,7,false) -> 2.8 | G11: =VLOOKUP(TRIM($B$4&$A$7&$B$8&C11),raw_weights!A:H,8,false) -> 0.3
C12: =weights_editor!C8 -> Mentoring | D12: =VLOOKUP(TRIM($B$4&$A$7&$B$8&C12),raw_weights!A:I,9,false) -> You have mentored several junior engineers around code quality. | E12: 1 | F12: =VLOOKUP(TRIM($B$4&$A$7&$B$8&C12),raw_weights!A:H,7,false) -> 1.5 | G12: =VLOOKUP(TRIM($B$4&$A$7&$B$8&C12),raw_weights!A:H,8,false) -> 0.1
B13: =weights_editor!B9 -> Testing | D13: =VLOOKUP(TRIM($B$4&$A$7&B13&C13),raw_weights!A:I,9,false) -> The ability to understand and implement great testing practices. Independently testing, advising the rest of the team on quality of tests. | E13: =E14*G14+E15*G15+E16*G16+E17*G17+E18*G18 -> 1 | F13: =VLOOKUP(TRIM($B$4&$A$7&B13&C13),raw_weights!A:H,7,false) -> 2.92 | G13: =VLOOKUP(TRIM($B$4&$A$7&B13&C13),raw_weights!A:H,8,false) -> 0.15
C14: =weights_editor!C10 -> Testing your code | D14: =VLOOKUP(TRIM($B$4&$A$7&$B$13&C14),raw_weights!A:I,9,false) -> You always write full tests for your code unassisted, covering all edge cases even with complex functionality. | E14: 1 | F14: =VLOOKUP(TRIM($B$4&$A$7&$B$13&C14),raw_weights!A:H,7,false) -> 3.2 | G14: =VLOOKUP(TRIM($B$4&$A$7&$B$13&C14),raw_weights!A:H,8,false) -> 0.5
C15: =weights_editor!C11 -> Improving coverage | D15: =VLOOKUP(TRIM($B$4&$A$7&$B$13&C15),raw_weights!A:I,9,false) -> You've worked to improve the quality of your own and your team's test coverage. | E15: 1 | F15: =VLOOKUP(TRIM($B$4&$A$7&$B$13&C15),raw_weights!A:H,7,false) -> 2.8 | G15: =VLOOKUP(TRIM($B$4&$A$7&$B$13&C15),raw_weights!A:H,8,false) -> 0.3
C16: =weights_editor!C12 -> Taking responsibility | D16: =VLOOKUP(TRIM($B$4&$A$7&$B$13&C16),raw_weights!A:I,9,false) -> You consistently look for and can recall quality metrics to demonstrate your test coverage, and monitor in behalf of your team. | E16: 1 | F16: =VLOOKUP(TRIM($B$4&$A$7&$B$13&C16),raw_weights!A:H,7,false) -> 2.4 | G16: =VLOOKUP(TRIM($B$4&$A$7&$B$13&C16),raw_weights!A:H,8,false) -> 0.2
C17: =weights_editor!C13 -> Leading testing strategy | D17: =VLOOKUP(TRIM($B$4&$A$7&$B$13&C17),raw_weights!A:I,9,false) -> N/A | E17: 0 | F17: =VLOOKUP(TRIM($B$4&$A$7&$B$13&C17),raw_weights!A:H,7,false) -> 1 | G17: =VLOOKUP(TRIM($B$4&$A$7&$B$13&C17),raw_weights!A:H,8,false) -> 0
C18: =weights_editor!C14 -> Advocating for testing | D18: =VLOOKUP(TRIM($B$4&$A$7&$B$13&C18),raw_weights!A:I,9,false) -> N/A | E18: 0 | F18: =VLOOKUP(TRIM($B$4&$A$7&$B$13&C18),raw_weights!A:H,7,false) -> 1 | G18: =VLOOKUP(TRIM($B$4&$A$7&$B$13&C18),raw_weights!A:H,8,false) -> 0
B19: =weights_editor!B15 -> Technical Understanding & Prioritisation | D19: =VLOOKUP(TRIM($B$4&$A$7&B19&C19),raw_weights!A:I,9,false) -> The ability to develop technical understanding and use this to prioritise tasks appropriately. Is a technical and prioritisation leader within the team, including taking some ownership of other team members' technical growth and development. | E19: =E20*G20+E21*G21+E22*G22+E23*G23 -> 1.6 | F19: =VLOOKUP(TRIM($B$4&$A$7&B19&C19),raw_weights!A:H,7,false) -> 2.46 | G19: =VLOOKUP(TRIM($B$4&$A$7&B19&C19),raw_weights!A:H,8,false) -> 0.15
C20: =weights_editor!C16 -> Understanding code | D20: =VLOOKUP(TRIM($B$4&$A$7&$B$19&C20),raw_weights!A:I,9,false) -> You understand your team's domain at a high level, including the breadth of services, how they interact, and data flows between systems. You understand adjacent domains as they affect your team. | E20: 2 | F20: =VLOOKUP(TRIM($B$4&$A$7&$B$19&C20),raw_weights!A:H,7,false) -> 2.2 | G20: =VLOOKUP(TRIM($B$4&$A$7&$B$19&C20),raw_weights!A:H,8,false) -> 0.55
C21: =weights_editor!C17 -> Technical collaboration | D21: =VLOOKUP(TRIM($B$4&$A$7&$B$19&C21),raw_weights!A:I,9,false) -> You actively facilitate technical discussions between team members and have a deep familiarity with technical topics under discussion | E21: 1 | F21: =VLOOKUP(TRIM($B$4&$A$7&$B$19&C21),raw_weights!A:H,7,false) -> 2.6 | G21: =VLOOKUP(TRIM($B$4&$A$7&$B$19&C21),raw_weights!A:H,8,false) -> 0.25
C22: =weights_editor!C18 -> Work breakdown | D22: =VLOOKUP(TRIM($B$4&$A$7&$B$19&C22),raw_weights!A:I,9,false) -> You review projects critically, ensuring they are appropriately delineated and understood by the team. | E22: 1 | F22: =VLOOKUP(TRIM($B$4&$A$7&$B$19&C22),raw_weights!A:H,7,false) -> 2.4 | G22: =VLOOKUP(TRIM($B$4&$A$7&$B$19&C22),raw_weights!A:H,8,false) -> 0.15
C23: =weights_editor!C19 -> Task prioritisation | D23: =VLOOKUP(TRIM($B$4&$A$7&$B$19&C23),raw_weights!A:I,9,false) -> You ensure tasks are prioritised correctly, and that dependencies are noted and well understood by the team, including at the epic level. You foster a culture of priority setting and highlight the importance of alignment with organizational strategy | E23: 1 | F23: =VLOOKUP(TRIM($B$4&$A$7&$B$19&C23),raw_weights!A:H,7,false) -> 2.4 | G23: =VLOOKUP(TRIM($B$4&$A$7&$B$19&C23),raw_weights!A:H,8,false) -> 0.1
B24: =weights_editor!B20 -> Software Architecture | D24: =VLOOKUP(TRIM($B$4&$A$7&B24&C24),raw_weights!A:I,9,false) -> The ability to interact and engage with architectural approaches of the organization. Is able to consistently design code that is aligned with the overall service architecture. | E24: =E25*G25+E26*G26+E27*G27+E28*G28+E29*G29 -> 2.1 | F24: =VLOOKUP(TRIM($B$4&$A$7&B24&C24),raw_weights!A:H,7,false) -> 2.17 | G24: =VLOOKUP(TRIM($B$4&$A$7&B24&C24),raw_weights!A:H,8,false) -> 0.15
C25: =weights_editor!C21 -> Reaction to feedback | D25: =VLOOKUP(TRIM($B$4&$A$7&$B$24&C25),raw_weights!A:I,9,false) -> N/A | E25: 4 | F25: =VLOOKUP(TRIM($B$4&$A$7&$B$24&C25),raw_weights!A:H,7,false) -> 3 | G25: =VLOOKUP(TRIM($B$4&$A$7&$B$24&C25),raw_weights!A:H,8,false) -> 0.2
C26: =weights_editor!C22 -> Code | D26: =VLOOKUP(TRIM($B$4&$A$7&$B$24&C26),raw_weights!A:I,9,false) -> You are able to utilize abstractions and code isolation effectively. | E26: 2 | F26: =VLOOKUP(TRIM($B$4&$A$7&$B$24&C26),raw_weights!A:H,7,false) -> 2.6 | G26: =VLOOKUP(TRIM($B$4&$A$7&$B$24&C26),raw_weights!A:H,8,false) -> 0.2
C27: =weights_editor!C23 -> Design | D27: =VLOOKUP(TRIM($B$4&$A$7&$B$24&C27),raw_weights!A:I,9,false) -> You have deep architectural and design pattern experience. You consult with team members only on more difficult designs. You set up new projects to ensure architectural success by anticipating future use cases and making design decisions that minimize the cost of future changes | E27: 1 | F27: =VLOOKUP(TRIM($B$4&$A$7&$B$24&C27),raw_weights!A:H,7,false) -> 1.5 | G27: =VLOOKUP(TRIM($B$4&$A$7&$B$24&C27),raw_weights!A:H,8,false) -> 0.3
C28: =weights_editor!C24 -> Development | D28: =VLOOKUP(TRIM($B$4&$A$7&$B$24&C28),raw_weights!A:I,9,false) -> N/A | E28: 2 | F28: =VLOOKUP(TRIM($B$4&$A$7&$B$24&C28),raw_weights!A:H,7,false) -> 2 | G28: =VLOOKUP(TRIM($B$4&$A$7&$B$24&C28),raw_weights!A:H,8,false) -> 0.3
C29: =weights_editor!C25 -> Technical debt | D29: =VLOOKUP(TRIM($B$4&$A$7&$B$24&C29),raw_weights!A:I,9,false) -> You make plans with technical debt in mind, and how you will pay it down incrementally and consistently. You advise other team members on recognising and considering it | E29: 2 | F29: =VLOOKUP(TRIM($B$4&$A$7&$B$24&C29),raw_weights!A:H,7,false) -> 2.1 | G29: =VLOOKUP(TRIM($B$4&$A$7&$B$24&C29),raw_weights!A:H,8,false) -> 0
B30: =weights_editor!B26 -> Security | D30: =VLOOKUP(TRIM($B$4&$A$7&B30&C30),raw_weights!A:I,9,false) -> The ability to understand and apply security principles, handle user data appropriately and report security concerns. Consistently approaches all engineering work with a security lens. | E30: =E31*G31+E32*G32+E33*G33+E34*G34+E35*G35+E36*G36 -> 2.9 | F30: =VLOOKUP(TRIM($B$4&$A$7&B30&C30),raw_weights!A:H,7,false) -> 2.71 | G30: =VLOOKUP(TRIM($B$4&$A$7&B30&C30),raw_weights!A:H,8,false) -> 0.1
C31: =weights_editor!C27 -> Knowledge | D31: =VLOOKUP(TRIM($B$4&$A$7&$B$30&C31),raw_weights!A:I,9,false) -> You have an excellent understanding of security principles and you work to better facilitate the team's understanding. | E31: 4 | F31: =VLOOKUP(TRIM($B$4&$A$7&$B$30&C31),raw_weights!A:H,7,false) -> 2.8 | G31: =VLOOKUP(TRIM($B$4&$A$7&$B$30&C31),raw_weights!A:H,8,false) -> 0.3
C32: =weights_editor!C28 -> User data | D32: =VLOOKUP(TRIM($B$4&$A$7&$B$30&C32),raw_weights!A:I,9,false) -> You have faultless handling of user data, and set an example for others within the team. | E32: 3 | F32: =VLOOKUP(TRIM($B$4&$A$7&$B$30&C32),raw_weights!A:H,7,false) -> 3.1 | G32: =VLOOKUP(TRIM($B$4&$A$7&$B$30&C32),raw_weights!A:H,8,false) -> 0.3
C33: =weights_editor!C29 -> Reporting | D33: =VLOOKUP(TRIM($B$4&$A$7&$B$30&C33),raw_weights!A:I,9,false) -> N/A | E33: 2 | F33: =VLOOKUP(TRIM($B$4&$A$7&$B$30&C33),raw_weights!A:H,7,false) -> 2.6 | G33: =VLOOKUP(TRIM($B$4&$A$7&$B$30&C33),raw_weights!A:H,8,false) -> 0.2
C34: =weights_editor!C30 -> Proactivity | D34: =VLOOKUP(TRIM($B$4&$A$7&$B$30&C34),raw_weights!A:I,9,false) -> You actively look for security vulnerabilities both in the code and when providing peer reviews. | E34: 2 | F34: =VLOOKUP(TRIM($B$4&$A$7&$B$30&C34),raw_weights!A:H,7,false) -> 2.1 | G34: =VLOOKUP(TRIM($B$4&$A$7&$B$30&C34),raw_weights!A:H,8,false) -> 0.2
C35: =weights_editor!C31 -> Collaboration | D35: =VLOOKUP(TRIM($B$4&$A$7&$B$30&C35),raw_weights!A:I,9,false) -> You work with the security teams to help refine technical strategy. | E35: 1 | F35: =VLOOKUP(TRIM($B$4&$A$7&$B$30&C35),raw_weights!A:H,7,false) -> 2.4 | G35: =VLOOKUP(TRIM($B$4&$A$7&$B$30&C35),raw_weights!A:H,8,false) -> 0
C36: =weights_editor!C32 -> Strategy | D36: =VLOOKUP(TRIM($B$4&$A$7&$B$30&C36),raw_weights!A:I,9,false) -> N/A | E36: 2 | F36: =VLOOKUP(TRIM($B$4&$A$7&$B$30&C36),raw_weights!A:H,7,false) -> 1.5 | G36: =VLOOKUP(TRIM($B$4&$A$7&$B$30&C36),raw_weights!A:H,8,false) -> 0
B37: =weights_editor!B33 -> Debugging & Monitoring | D37: =VLOOKUP(TRIM($B$4&$A$7&B37&C37),raw_weights!A:I,9,false) -> The ability to understand and implement systematic debugging and monitoring practices to diagnose issues. Uses systematic debugging to diagnose all issues located to a single service and drives monitoring work across the team. | E37: =E38*G38+E39*G39+E40*G40+E41*G41+E42*G42+E43*G43 -> 1.6 | F37: =VLOOKUP(TRIM($B$4&$A$7&B37&C37),raw_weights!A:H,7,false) -> 2.525 | G37: =VLOOKUP(TRIM($B$4&$A$7&B37&C37),raw_weights!A:H,8,false) -> 0.1
C38: =weights_editor!C34 -> Debugging | D38: =VLOOKUP(TRIM($B$4&$A$7&$B$37&C38),raw_weights!A:I,9,false) -> You use systematic debugging to diagnose cross service issues, sometimes with help from more senior engineers. | E38: 2 | F38: =VLOOKUP(TRIM($B$4&$A$7&$B$37&C38),raw_weights!A:H,7,false) -> 2.8 | G38: =VLOOKUP(TRIM($B$4&$A$7&$B$37&C38),raw_weights!A:H,8,false) -> 0.4
C39: =weights_editor!C35 -> Tools | D39: =VLOOKUP(TRIM($B$4&$A$7&$B$37&C39),raw_weights!A:I,9,false) -> You can judge whether a new tool is necessary to instrument and monitor systems. You can create that tool if required. | E39: 2 | F39: =VLOOKUP(TRIM($B$4&$A$7&$B$37&C39),raw_weights!A:H,7,false) -> 2.6 | G39: =VLOOKUP(TRIM($B$4&$A$7&$B$37&C39),raw_weights!A:H,8,false) -> 0.2
C40: =weights_editor!C36 -> Philosophy | D40: =VLOOKUP(TRIM($B$4&$A$7&$B$37&C40),raw_weights!A:I,9,false) -> You understand the cross-functional and cross-organization implications of your team's monitoring philosophy. You proactively seek to refine the monitoring philosophy of your team. | E40: 1 | F40: =VLOOKUP(TRIM($B$4&$A$7&$B$37&C40),raw_weights!A:H,7,false) -> 2.1 | G40: =VLOOKUP(TRIM($B$4&$A$7&$B$37&C40),raw_weights!A:H,8,false) -> 0.2
C41: =weights_editor!C37 -> Data | D41: =VLOOKUP(TRIM($B$4&$A$7&$B$37&C41),raw_weights!A:I,9,false) -> You are aware of the operational data for your team and use it as a basis for driving changes to your team's services to achieve stability and performance improvements. | E41: 1 | F41: =VLOOKUP(TRIM($B$4&$A$7&$B$37&C41),raw_weights!A:H,7,false) -> 2.4 | G41: =VLOOKUP(TRIM($B$4&$A$7&$B$37&C41),raw_weights!A:H,8,false) -> 0.15
C42: =weights_editor!C38 -> Profiling | D42: =VLOOKUP(TRIM($B$4&$A$7&$B$37&C42),raw_weights!A:I,9,false) -> N/A | E42: 1 | F42: =VLOOKUP(TRIM($B$4&$A$7&$B$37&C42),raw_weights!A:H,7,false) -> 2.1 | G42: =VLOOKUP(TRIM($B$4&$A$7&$B$37&C42),raw_weights!A:H,8,false) -> 0.05
C43: =weights_editor!C39 -> Mentoring | D43: =VLOOKUP(TRIM($B$4&$A$7&$B$37&C43),raw_weights!A:I,9,false) -> You act as a primary mentor for the rest of their team on running systems. | E43: 1 | F43: =VLOOKUP(TRIM($B$4&$A$7&$B$37&C43),raw_weights!A:H,7,false) -> 1 | G43: =VLOOKUP(TRIM($B$4&$A$7&$B$37&C43),raw_weights!A:H,8,false) -> 0
A44: =weights_editor!A41 -> SOFT SKILLS | E44: =(E45*G45+E50*G50+E55*G55+E59*G59+E64*G64) -> 1.91 | F44: =VLOOKUP(TRIM($B$4&$A$44&B44&C44),raw_weights!A:H,7,false) -> 2.264 | G44: =VLOOKUP(TRIM($B$4&$A$44&B44&C44),raw_weights!A:H,8,false) -> 0.3
B45: =weights_editor!B42 -> Empathy & Humility | D45: =VLOOKUP(TRIM($B$4&$A$44&B45&C45),raw_weights!A:I,9,false) -> The ability to share someone else's feelings or experiences by imagining what it would be like to be in that person's situation. A great person to have in any room. Trusted by peers and their team. Can take any problem team and help them drive in the same direction. | E45: =E46*G46+E47*G47+E48*G48+E49*G49 -> 1.6 | F45: =VLOOKUP(TRIM($B$4&$A$44&B45&C45),raw_weights!A:H,7,false) -> 2.31 | G45: =VLOOKUP(TRIM($B$4&$A$44&B45&C45),raw_weights!A:H,8,false) -> 0.4
C46: =weights_editor!C43 -> Credit and blame | D46: =VLOOKUP(TRIM($B$4&$A$44&$B$45&C46),raw_weights!A:I,9,false) -> You're an ally to your peers and wider team, protecting them from undue blame and pushing praise onto them. You regularly look for opportunities to give praise publicly. | E46: 2 | F46: =VLOOKUP(TRIM($B$4&$A$44&$B$45&C46),raw_weights!A:H,7,false) -> 2.6 | G46: =VLOOKUP(TRIM($B$4&$A$44&$B$45&C46),raw_weights!A:H,8,false) -> 0.3
C47: =weights_editor!C44 -> Understanding others | D47: =VLOOKUP(TRIM($B$4&$A$44&$B$45&C47),raw_weights!A:I,9,false) -> You are able to recognise bias in others and help them to see their peers, customers or stakeholders through fresh eyes. | E47: 2 | F47: =VLOOKUP(TRIM($B$4&$A$44&$B$45&C47),raw_weights!A:H,7,false) -> 2.7 | G47: =VLOOKUP(TRIM($B$4&$A$44&$B$45&C47),raw_weights!A:H,8,false) -> 0.3
C48: =weights_editor!C45 -> Mediation and facilitation | D48: =VLOOKUP(TRIM($B$4&$A$44&$B$45&C48),raw_weights!A:I,9,false) -> You help teams within your organisation get closer to each other and understand each other's viewpoints. | E48: 1 | F48: =VLOOKUP(TRIM($B$4&$A$44&$B$45&C48),raw_weights!A:H,7,false) -> 2.1 | G48: =VLOOKUP(TRIM($B$4&$A$44&$B$45&C48),raw_weights!A:H,8,false) -> 0.2
C49: =weights_editor!C46 -> Mentoring | D49: =VLOOKUP(TRIM($B$4&$A$44&$B$45&C49),raw_weights!A:I,9,false) -> You've proactively developed multiple informal or formal mentoring relationship through your ability to understand a peer or subordinate. | E49: 1 | F49: =VLOOKUP(TRIM($B$4&$A$44&$B$45&C49),raw_weights!A:H,7,false) -> 1.5 | G49: =VLOOKUP(TRIM($B$4&$A$44&$B$45&C49),raw_weights!A:H,8,false) -> 0.2
B50: =weights_editor!B47 -> Communication | D50: =VLOOKUP(TRIM($B$4&$A$44&B50&C50),raw_weights!A:I,9,false) -> The ability to communicate well with those around you with sensitivity to timeliness, medium, brevity and tone. Communicates with organisation, helps others in team to communicate. | E50: =E51*G51+E52*G52+E53*G53+E54*G54 -> 2.2 | F50: =VLOOKUP(TRIM($B$4&$A$44&B50&C50),raw_weights!A:H,7,false) -> 1.96 | G50: =VLOOKUP(TRIM($B$4&$A$44&B50&C50),raw_weights!A:H,8,false) -> 0.2
C51: =weights_editor!C48 -> Keeping people informed | D51: =VLOOKUP(TRIM($B$4&$A$44&$B$50&C51),raw_weights!A:I,9,false) -> You communicate on behalf of your team to the broader organisation on important or divisive projects, handling any questions in a timely manner. | E51: 2 | F51: =VLOOKUP(TRIM($B$4&$A$44&$B$50&C51),raw_weights!A:H,7,false) -> 2 | G51: =VLOOKUP(TRIM($B$4&$A$44&$B$50&C51),raw_weights!A:H,8,false) -> 0.5
C52: =weights_editor!C49 -> Looking for feedback | D52: =VLOOKUP(TRIM($B$4&$A$44&$B$50&C52),raw_weights!A:I,9,false) -> You proactively ask for feedback from important stakeholders in your organisation early in your work. | E52: 3 | F52: =VLOOKUP(TRIM($B$4&$A$44&$B$50&C52),raw_weights!A:H,7,false) -> 2.8 | G52: =VLOOKUP(TRIM($B$4&$A$44&$B$50&C52),raw_weights!A:H,8,false) -> 0.2
C53: =weights_editor!C50 -> Delivering bad news | D53: =VLOOKUP(TRIM($B$4&$A$44&$B$50&C53),raw_weights!A:I,9,false) -> You communicate changes of plan or slip in timelines to a broad group within your organisation and manage expectations effectively until resolution. | E53: 2 | F53: =VLOOKUP(TRIM($B$4&$A$44&$B$50&C53),raw_weights!A:H,7,false) -> 1.5 | G53: =VLOOKUP(TRIM($B$4&$A$44&$B$50&C53),raw_weights!A:H,8,false) -> 0.2
C54: =weights_editor!C51 -> Mentoring communicators | D54: =VLOOKUP(TRIM($B$4&$A$44&$B$50&C54),raw_weights!A:I,9,false) -> You set up processes around more effective communication for your immediate team, and manage its implementation. You proactively offer good feedback to peers on their communication methods. | E54: 2 | F54: =VLOOKUP(TRIM($B$4&$A$44&$B$50&C54),raw_weights!A:H,7,false) -> 1 | G54: =VLOOKUP(TRIM($B$4&$A$44&$B$50&C54),raw_weights!A:H,8,false) -> 0.1
B55: =weights_editor!B52 -> Initiative | D55: =VLOOKUP(TRIM($B$4&$A$44&B55&C55),raw_weights!A:I,9,false) -> The ability to use your judgment to make decisions and do things without needing to be told what to do. Refuses to believe that anything is unachievable. Infectious desire to activate and progress. Drives others to create their best work. Like a rocket: just light the fuse. | E55: =E56*G56+E57*G57+E58*G58 -> 2 | F55: =VLOOKUP(TRIM($B$4&$A$44&B55&C55),raw_weights!A:H,7,false) -> 2.45 | G55: =VLOOKUP(TRIM($B$4&$A$44&B55&C55),raw_weights!A:H,8,false) -> 0.2
C56: =weights_editor!C53 -> Can-do attitude | D56: =VLOOKUP(TRIM($B$4&$A$44&$B$55&C56),raw_weights!A:I,9,false) -> You're constantly creating new opportunities for yourself and those around you. Your team is celebrated for innovation as a result of your contributions. | E56: 2 | F56: =VLOOKUP(TRIM($B$4&$A$44&$B$55&C56),raw_weights!A:H,7,false) -> 2.8 | G56: =VLOOKUP(TRIM($B$4&$A$44&$B$55&C56),raw_weights!A:H,8,false) -> 0.5
C57: =weights_editor!C54 -> Pro-activity in seeking help | D57: =VLOOKUP(TRIM($B$4&$A$44&$B$55&C57),raw_weights!A:I,9,false) -> You recognise a lack of expertise in yourself and your organisation, and pro-actively found that expertise in areas not given to you. This leads to a successful outcome on more than one occasion. | E57: 1 | F57: =VLOOKUP(TRIM($B$4&$A$44&$B$55&C57),raw_weights!A:H,7,false) -> 2.4 | G57: =VLOOKUP(TRIM($B$4&$A$44&$B$55&C57),raw_weights!A:H,8,false) -> 0.25
C58: =weights_editor!C55 -> Follow through | D58: =VLOOKUP(TRIM($B$4&$A$44&$B$55&C58),raw_weights!A:I,9,false) -> You adapt your skillset and knowledge to lead large or complex projects to a successful outcome. | E58: 3 | F58: =VLOOKUP(TRIM($B$4&$A$44&$B$55&C58),raw_weights!A:H,7,false) -> 1.8 | G58: =VLOOKUP(TRIM($B$4&$A$44&$B$55&C58),raw_weights!A:H,8,false) -> 0.25
B59: =weights_editor!B56 -> Objectivity & Adaptability | D59: =VLOOKUP(TRIM($B$4&$A$44&B59&C59),raw_weights!A:I,9,false) -> The ability to deal with problems based on conditions that really exist, rather than following fixed theories, ideas, or rules, and to adapt to suit different conditions. Can take problems outside their skillset and quickly adapt to solve them. Helps other peers to do the same. | E59: =E60*G60+E61*G61+E62*G62+E63*G63 -> 2.3 | F59: =VLOOKUP(TRIM($B$4&$A$44&B59&C59),raw_weights!A:H,7,false) -> 2.78 | G59: =VLOOKUP(TRIM($B$4&$A$44&B59&C59),raw_weights!A:H,8,false) -> 0.1
C60: =weights_editor!C57 -> Efficient decision-making | D60: =VLOOKUP(TRIM($B$4&$A$44&$B$59&C60),raw_weights!A:I,9,false) -> You help your team to make decisions in a more timely manner, breaking down assumptions about the shape of the work and encouraging people to value done over perfect. | E60: 2 | F60: =VLOOKUP(TRIM($B$4&$A$44&$B$59&C60),raw_weights!A:H,7,false) -> 2.6 | G60: =VLOOKUP(TRIM($B$4&$A$44&$B$59&C60),raw_weights!A:H,8,false) -> 0.5
C61: =weights_editor!C58 -> Self improvement | D61: =VLOOKUP(TRIM($B$4&$A$44&$B$59&C61),raw_weights!A:I,9,false) -> You can point to several areas of improvement resulting from your focus on improving development areas over time. | E61: 4 | F61: =VLOOKUP(TRIM($B$4&$A$44&$B$59&C61),raw_weights!A:H,7,false) -> 3.5 | G61: =VLOOKUP(TRIM($B$4&$A$44&$B$59&C61),raw_weights!A:H,8,false) -> 0.2
C62: =weights_editor!C59 -> Objectivity | D62: =VLOOKUP(TRIM($B$4&$A$44&$B$59&C62),raw_weights!A:I,9,false) -> You are positive in the face of dramatic changes of plans. Curveballs are dealt with sensibly without frustration. | E62: 2 | F62: =VLOOKUP(TRIM($B$4&$A$44&$B$59&C62),raw_weights!A:H,7,false) -> 2.7 | G62: =VLOOKUP(TRIM($B$4&$A$44&$B$59&C62),raw_weights!A:H,8,false) -> 0.2
C63: =weights_editor!C60 -> Time management | D63: =VLOOKUP(TRIM($B$4&$A$44&$B$59&C63),raw_weights!A:I,9,false) -> You're in control of your calendar. You take no issue with not being involved in a project or meeting if it means saving you time. | E63: 1 | F63: =VLOOKUP(TRIM($B$4&$A$44&$B$59&C63),raw_weights!A:H,7,false) -> 2.4 | G63: =VLOOKUP(TRIM($B$4&$A$44&$B$59&C63),raw_weights!A:H,8,false) -> 0.1
B64: =weights_editor!B61 -> Business Acumen | D64: =VLOOKUP(TRIM($B$4&$A$44&B64&C64),raw_weights!A:I,9,false) | E64: =E65*G65 -> 2 | F64: =VLOOKUP(TRIM($B$4&$A$44&B64&C64),raw_weights!A:H,7,false) -> 1.8 | G64: =VLOOKUP(TRIM($B$4&$A$44&B64&C64),raw_weights!A:H,8,false) -> 0.1
C65: =weights_editor!C62 -> Understanding level | D65: =VLOOKUP(TRIM($B$4&$A$44&$B$64&C65),raw_weights!A:I,9,false) -> Has a thorough understanding of their team's domain, and how it contributes to overall business strategy. Has a basic understanding of adjacent teams' business domains. | E65: 2 | F65: =VLOOKUP(TRIM($B$4&$A$44&$B$64&C65),raw_weights!A:H,7,false) -> 1.8 | G65: =VLOOKUP(TRIM($B$4&$A$44&$B$64&C65),raw_weights!A:H,8,false) -> 1
A66: =weights_editor!A64 -> LEADERSHIP | E66: =(E67*G67+E71*G71+E76*G76+E81*G81+E86*G86) -> 2.405 | F66: =VLOOKUP(TRIM($B$4&$A$66&B66&C66),raw_weights!A:H,7,false) -> 1.2755 | G66: =VLOOKUP(TRIM($B$4&$A$66&B66&C66),raw_weights!A:H,8,false) -> 0.1
B67: =weights_editor!B65 -> Hiring and Org Design | D67: =VLOOKUP(TRIM($B$4&$A$66&B67&C67),raw_weights!A:I,9,false) -> The ability to understand the needs of the business and ensure that your team can meet them. A competent interviewer. Able to follow a structured hiring process, and make a decision. | E67: =E68*G68+E69*G69+E70*G70 -> 2.4 | F67: =VLOOKUP(TRIM($B$4&$A$66&B67&C67),raw_weights!A:H,7,false) -> 0.48 | G67: =VLOOKUP(TRIM($B$4&$A$66&B67&C67),raw_weights!A:H,8,false) -> 0.3
C68: =weights_editor!C66 -> Deploying Teams | D68: =VLOOKUP(TRIM($B$4&$A$66&$B$67&C68),raw_weights!A:I,9,false) -> You've carved out an additional role for yourself or peers to fulfil a need that a team has. | E68: 3 | F68: =VLOOKUP(TRIM($B$4&$A$66&$B$67&C68),raw_weights!A:H,7,false) -> 0.2 | G68: =VLOOKUP(TRIM($B$4&$A$66&$B$67&C68),raw_weights!A:H,8,false) -> 0.4
C69: =weights_editor!C67 -> Employer Brand | D69: =VLOOKUP(TRIM($B$4&$A$66&$B$67&C69),raw_weights!A:I,9,false) -> You've helped to establish the company as a good employer through promotion on stage or online. You've inputted into the company's careers pages. | E69: 2 | F69: =VLOOKUP(TRIM($B$4&$A$66&$B$67&C69),raw_weights!A:H,7,false) -> 1 | G69: =VLOOKUP(TRIM($B$4&$A$66&$B$67&C69),raw_weights!A:H,8,false) -> 0.4
C70: =weights_editor!C68 -> Hiring | D70: =VLOOKUP(TRIM($B$4&$A$66&$B$67&C70),raw_weights!A:I,9,false) -> You are regularly part of hiring panels, and have been hiring manager for at least one hire that passed probation. | E70: 2 | F70: =VLOOKUP(TRIM($B$4&$A$66&$B$67&C70),raw_weights!A:H,7,false) -> 0 | G70: =VLOOKUP(TRIM($B$4&$A$66&$B$67&C70),raw_weights!A:H,8,false) -> 0.2
B71: =weights_editor!B69 -> Stakeholder Management | D71: =VLOOKUP(TRIM($B$4&$A$66&B71&C71),raw_weights!A:I,9,false) -> The ability to ensure that teams are protected and expectations are set correctly. Is able to proactively inform stakeholders both within and outside the organisation with pertinent and timely information, including bad news. Able to read and adapt to personalities across the organisation. Has good relationships with all key stakeholders. | E71: =E72*G72+E73*G73+E74*G74+E75*G75 -> 2.7 | F71: =VLOOKUP(TRIM($B$4&$A$66&B71&C71),raw_weights!A:H,7,false) -> 1.97 | G71: =VLOOKUP(TRIM($B$4&$A$66&B71&C71),raw_weights!A:H,8,false) -> 0.3
C72: =weights_editor!C70 -> Managing Goals and Expectations | D72: =VLOOKUP(TRIM($B$4&$A$66&$B$71&C72),raw_weights!A:I,9,false) -> You lead multiple larger projects with external clients or internal stakeholders, including managing bad news and scope creep or timeline slippage, with successful outcomes. | E72: 3 | F72: =VLOOKUP(TRIM($B$4&$A$66&$B$71&C72),raw_weights!A:H,7,false) -> 1.7 | G72: =VLOOKUP(TRIM($B$4&$A$66&$B$71&C72),raw_weights!A:H,8,false) -> 0.4
C73: =weights_editor!C71 -> Foresight | D73: =VLOOKUP(TRIM($B$4&$A$66&$B$71&C73),raw_weights!A:I,9,false) -> You look for misalignment across large scopes of work involving multiple clients or stakeholders, and ensure that they're smoothed out in advance. | E73: 2 | F73: =VLOOKUP(TRIM($B$4&$A$66&$B$71&C73),raw_weights!A:H,7,false) -> 2 | G73: =VLOOKUP(TRIM($B$4&$A$66&$B$71&C73),raw_weights!A:H,8,false) -> 0.3
C74: =weights_editor!C72 -> Engendering Trust | D74: =VLOOKUP(TRIM($B$4&$A$66&$B$71&C74),raw_weights!A:I,9,false) -> You've repeatedly proven yourself able to work closely with clients or stakeholders in ways that earn respect and results. You use their time wisely and lean into their knowledge. | E74: 4 | F74: =VLOOKUP(TRIM($B$4&$A$66&$B$71&C74),raw_weights!A:H,7,false) -> 2.4 | G74: =VLOOKUP(TRIM($B$4&$A$66&$B$71&C74),raw_weights!A:H,8,false) -> 0.2
C75: =weights_editor!C73 -> Protecting the Team | D75: =VLOOKUP(TRIM($B$4&$A$66&$B$71&C75),raw_weights!A:I,9,false) -> You protect direct reports from difficult stakeholders across multiple projects. | E75: 1 | F75: =VLOOKUP(TRIM($B$4&$A$66&$B$71&C75),raw_weights!A:H,7,false) -> 2.1 | G75: =VLOOKUP(TRIM($B$4&$A$66&$B$71&C75),raw_weights!A:H,8,false) -> 0.1
B76: =weights_editor!B74 -> Team Leadership | D76: =VLOOKUP(TRIM($B$4&$A$66&B76&C76),raw_weights!A:I,9,false) -> The ability to maintain quality, efficiency and establish trust in your ability. Capable of informally managing interns, contractors, suppliers and agencies. Possibly manages one or two junior team members. Doesn't look for glory, and doesn't complain about boring work. Assumes good decisions in others work. Broadly does what they say they're going to do. | E76: =E77*G77+E78*G78+E79*G79+E80*G80 -> 2.2 | F76: =VLOOKUP(TRIM($B$4&$A$66&B76&C76),raw_weights!A:H,7,false) -> 1.59 | G76: =VLOOKUP(TRIM($B$4&$A$66&B76&C76),raw_weights!A:H,8,false) -> 0.2
C77: =weights_editor!C75 -> Putting the Team first | D77: =VLOOKUP(TRIM($B$4&$A$66&$B$76&C77),raw_weights!A:I,9,false) -> You regularly make time for listening to and understanding the people you're responsible for. | E77: 3 | F77: =VLOOKUP(TRIM($B$4&$A$66&$B$76&C77),raw_weights!A:H,7,false) -> 2 | G77: =VLOOKUP(TRIM($B$4&$A$66&$B$76&C77),raw_weights!A:H,8,false) -> 0.5
C78: =weights_editor!C76 -> Difficult Conversations | D78: =VLOOKUP(TRIM($B$4&$A$66&$B$76&C78),raw_weights!A:I,9,false) -> You have helped someone on your team out with a difficult personal decision and acted in an objective, professional manner. | E78: 1 | F78: =VLOOKUP(TRIM($B$4&$A$66&$B$76&C78),raw_weights!A:H,7,false) -> 0.4 | G78: =VLOOKUP(TRIM($B$4&$A$66&$B$76&C78),raw_weights!A:H,8,false) -> 0.2
C79: =weights_editor!C77 -> Reliability | D79: =VLOOKUP(TRIM($B$4&$A$66&$B$76&C79),raw_weights!A:I,9,false) -> You have been open about your intentions when making a team-level decision – for example moving people between teams or introducing new role expectations – and followed through. | E79: 1 | F79: =VLOOKUP(TRIM($B$4&$A$66&$B$76&C79),raw_weights!A:H,7,false) -> 1.6 | G79: =VLOOKUP(TRIM($B$4&$A$66&$B$76&C79),raw_weights!A:H,8,false) -> 0.2
C80: =weights_editor!C78 -> Vulnerability | D80: =VLOOKUP(TRIM($B$4&$A$66&$B$76&C80),raw_weights!A:I,9,false) -> You have proactively admitted fault and weakness in yourself to team members, and admitted a mistake made in work you've done. | E80: 3 | F80: =VLOOKUP(TRIM($B$4&$A$66&$B$76&C80),raw_weights!A:H,7,false) -> 1.9 | G80: =VLOOKUP(TRIM($B$4&$A$66&$B$76&C80),raw_weights!A:H,8,false) -> 0.1
B81: =weights_editor!B79 -> Developing Others | D81: =VLOOKUP(TRIM($B$4&$A$66&B81&C81),raw_weights!A:I,9,false) -> The ability to develop the skillsets and abilities of your team. Able to recognise the strengths of peers, and look for ways to support those strengths through project work. Has invested time in materials or process to support team growth. Peers see them as an informal coach. | E81: =E82*G82+E83*G83+E84*G84+E85*G85 -> 2 | F81: =VLOOKUP(TRIM($B$4&$A$66&B81&C81),raw_weights!A:H,7,false) -> 0.93 | G81: =VLOOKUP(TRIM($B$4&$A$66&B81&C81),raw_weights!A:H,8,false) -> 0.15
C82: =weights_editor!C80 -> Identifying strengths | D82: =VLOOKUP(TRIM($B$4&$A$66&$B$81&C82),raw_weights!A:I,9,false) -> You recognise natural strengths in your peers which you help them to nurture. | E82: 3 | F82: =VLOOKUP(TRIM($B$4&$A$66&$B$81&C82),raw_weights!A:H,7,false) -> 0.8 | G82: =VLOOKUP(TRIM($B$4&$A$66&$B$81&C82),raw_weights!A:H,8,false) -> 0.3
C83: =weights_editor!C81 -> Supporting team growth | D83: =VLOOKUP(TRIM($B$4&$A$66&$B$81&C83),raw_weights!A:I,9,false) -> You support and champion peers in their personal growth, celebrating a promotion, successful project or praise from others. | E83: 1 | F83: =VLOOKUP(TRIM($B$4&$A$66&$B$81&C83),raw_weights!A:H,7,false) -> 0.8 | G83: =VLOOKUP(TRIM($B$4&$A$66&$B$81&C83),raw_weights!A:H,8,false) -> 0.4
C84: =weights_editor!C82 -> Investing in process | D84: =VLOOKUP(TRIM($B$4&$A$66&$B$81&C84),raw_weights!A:I,9,false) -> You invest in your future through a process of skills assessment to define your future direction. | E84: 2 | F84: =VLOOKUP(TRIM($B$4&$A$66&$B$81&C84),raw_weights!A:H,7,false) -> 1.3 | G84: =VLOOKUP(TRIM($B$4&$A$66&$B$81&C84),raw_weights!A:H,8,false) -> 0.2
C85: =weights_editor!C83 -> Feedback on work | D85: =VLOOKUP(TRIM($B$4&$A$66&$B$81&C85),raw_weights!A:I,9,false) -> Your feedback to peers on their work is honest, actionable and timely. You put the needs of the project over personal inhibitions. You're comfortable with having your mind changed. | E85: 3 | F85: =VLOOKUP(TRIM($B$4&$A$66&$B$81&C85),raw_weights!A:H,7,false) -> 1.1 | G85: =VLOOKUP(TRIM($B$4&$A$66&$B$81&C85),raw_weights!A:H,8,false) -> 0.1
B86: =weights_editor!B84 -> Culture & Togetherness | D86: =VLOOKUP(TRIM($B$4&$A$66&B86&C86),raw_weights!A:I,9,false) -> The ability to bring groups together and foster a happy and productive environment. Works to build and document behaviours they expect to see. Has trusted relationships with both junior colleagues and peers, and can describe where the organisation is strong or needs development. Organises regular team activities. | E86: =E87*G87+E88*G88+E89*G89 -> 2.7 | F86: =VLOOKUP(TRIM($B$4&$A$66&B86&C86),raw_weights!A:H,7,false) -> 1.66 | G86: =VLOOKUP(TRIM($B$4&$A$66&B86&C86),raw_weights!A:H,8,false) -> 0.05
C87: =weights_editor!C85 -> Setting an Example | D87: =VLOOKUP(TRIM($B$4&$A$66&$B$86&C87),raw_weights!A:I,9,false) -> You make an effort to document a cultural charter for your team, which you cite regularly and stick to rigorously. If you break your rules, you expect to be called out. | E87: 3 | F87: =VLOOKUP(TRIM($B$4&$A$66&$B$86&C87),raw_weights!A:H,7,false) -> 2.1 | G87: =VLOOKUP(TRIM($B$4&$A$66&$B$86&C87),raw_weights!A:H,8,false) -> 0.5
C88: =weights_editor!C86 -> Encouraging diverse opinions | D88: =VLOOKUP(TRIM($B$4&$A$66&$B$86&C88),raw_weights!A:I,9,false) -> You're leading efforts to improve diversity in your everyday environment, organising working groups, events and discussion across large parts of your organisation. | E88: 2 | F88: =VLOOKUP(TRIM($B$4&$A$66&$B$86&C88),raw_weights!A:H,7,false) -> 1.1 | G88: =VLOOKUP(TRIM($B$4&$A$66&$B$86&C88),raw_weights!A:H,8,false) -> 0.3
C89: =weights_editor!C87 -> Developing personal relationships | D89: =VLOOKUP(TRIM($B$4&$A$66&$B$86&C89),raw_weights!A:I,9,false) -> You make a point of knowing all about the people who report directly to you. You build close yet professional relationships with all direct reports fostering good levels of trust. | E89: 3 | F89: =VLOOKUP(TRIM($B$4&$A$66&$B$86&C89),raw_weights!A:H,7,false) -> 1.4 | G89: =VLOOKUP(TRIM($B$4&$A$66&$B$86&C89),raw_weights!A:H,8,false) -> 0.2
A90: OVERALL ASSESSMENT | G90: =SUM(G7,G44,G66) -> 1
C91: Engineering Craft | E91: =E7*G7 -> 0.903 | F91: =F7*G7 -> 1.5207
C92: Soft Skills | E92: =E44*G44 -> 0.573 | F92: =F44*G44 -> 0.6792
C93: Leadership | E93: =E66*G66 -> 0.2405 | F93: =F66*G66 -> 0.12755
C95: TOTAL WEIGHTED SCORE | E95: =SUM(E91:E93) -> 1.7165 | F95: =SUM(F91:F93) -> 2.32745
C97: Performance Rating | E97: =UPPER( IFS( F95=0, "N/A - No Role Model Rating", (E95/F95)*100 < 70, "Improvements Needed", (E95/F95)*100 < 90, "Developing Towards Great", (E95/F95)*100 <= 110, "Great Contribution", (E95/F95)*100 > 110, "Outstanding Contribution" )) -> DEVELOPING TOWARDS GREAT
A99: COMPANY VALUES ASSESSMENT
A100: Place Your Bets
B101: Decision Making
C102: Decides boldly acts quickly
C103: Fights inertia & Empowers action
C104: Iterates for impact & Challenges processes
A105: You're Welcome
...

Sheet weights_editor
D1: Junior Developer | G1: Confirmed Developer | J1: Senior Developer | M1: Staff Developer | P1: Senior Staff Developer | S1: Principal Developer
A2: Section | B2: Subsection | C2: Criteria | D2: Role Model Rating | E2: Weight | G2: Role Model Rating | H2: Weight | J2: Role Model Rating | K2: Weight | M2: Role Model Rating | N2: Weight | P2: Role Model Rating | Q2: Weight | S2: Role Model Rating | T2: Weight
A3: ENGINEERING CRAFT | D3: =D4*E4+D9*E9+D15*E15+D20*E20+D26*E26+D33*E33 -> 1.26 | E3: 0.7 | G3: =G4*H4+G9*H9+G15*H15+G20*H20+G26*H26+G33*H33 -> 1.9675 | H3: 0.65 | J3: =J4*K4+J9*K9+J15*K15+J20*K20+J26*K26+J33*K33 -> 2.5345 | K3: 0.6 | M3: =M4*N4+M9*N9+M15*N15+M20*N20+M26*N26+M33*N33 -> 2.9905 | N3: 0.4 | P3: =P4*Q4+P9*Q9+P15*Q15+P20*Q20+P26*Q26+P33*Q33 -> 3.64475 | Q3: 0.4 | S3: =S4*T4+S9*T9+S15*T15+S20*T20+S26*T26+S33*T33 -> 4 | T3: 0.4
A4: ENGINEERING CRAFT | B4: Writing Code | D4: =D5*E5+D6*E6+D7*E7+D8*E8 -> 1.2 | E4: 0.45 | G4: =G5*H5+G6*H6+G7*H7+G8*H8 -> 1.925 | H4: 0.4 | J4: =J5*K5+J6*K6+J7*K7+J8*K8 -> 2.51 | K4: 0.35 | M4: =M5*N5+M6*N6+M7*N7+M8*N8 -> 3.15 | N4: 0.3 | P4: =P5*Q5+P6*Q6+P7*Q7+P8*Q8 -> 3.61 | Q4: 0.3 | S4: =S5*T5+S6*T6+S7*T7+S8*T8 -> 4 | T4: 0.3
A5: ENGINEERING CRAFT | B5: Writing Code | C5: Quality | D5: 1.2 | E5: 0.5 | G5: 2 | H5: 0.45 | J5: 2.6 | K5: 0.4 | M5: 3.2 | N5: 0.4 | P5: 3.6 | Q5: 0.4 | S5: 4 | T5: 0.4
A6: ENGINEERING CRAFT | B6: Writing Code | C6: Documentation | D6: 1 | E6: 0.25 | G6: 1.8 | H6: 0.25 | J6: 2.4 | K6: 0.2 | M6: 3 | N6: 0.2 | P6: 3.4 | Q6: 0.2 | S6: 4 | T6: 0.2
A7: ENGINEERING CRAFT | B7: Writing Code | C7: Language | D7: 1.4 | E7: 0.25 | G7: 2.2 | H7: 0.25 | J7: 2.8 | K7: 0.3 | M7: 3.4 | N7: 0.3 | P7: 3.8 | Q7: 0.3 | S7: 4 | T7: 0.3
A8: ENGINEERING CRAFT | B8: Writing Code | C8: Mentoring | D8: 0 | E8: 0 | G8: 0.5 | H8: 0.05 | J8: 1.5 | K8: 0.1 | M8: 2.5 | N8: 0.1 | P8: 3.5 | Q8: 0.1 | S8: 4 | T8: 0.1
A9: ENGINEERING CRAFT | B9: Testing | D9: =D10*E10+D11*E11+D12*E12+D13*E13+D14*E14 -> 1.7 | E9: 0.15 | G9: =G10*H10+G11*H11+G12*H12+G13*H13+G14*H14 -> 2.45 | H9: 0.15 | J9: =J10*K10+J11*K11+J12*K12+J13*K13+J14*K14 -> 2.92 | K9: 0.15 | M9: =M10*N10+M11*N11+M12*N12+M13*N13+M14*N14 -> 2.5 | N9: 0.15 | P9: =P10*Q10+P11*Q11+P12*Q12+P13*Q13+P14*Q14 -> 3.6 | Q9: 0.15 | S9: =S10*T10+S11*T11+S12*T12+S13*T13+S14*T14 -> 4 | T9: 0.15
A10: ENGINEERING CRAFT | B10: Testing | C10: Testing your code | D10: 2 | E10: 0.7 | G10: 2.8 | H10: 0.6 | J10: 3.2 | K10: 0.5 | M10: 3.6 | N10: 0 | Q10: 0 | T10: 0
A11: ENGINEERING CRAFT | B11: Testing | C11: Improving coverage | D11: 1 | E11: 0.2 | G11: 2 | H11: 0.25 | J11: 2.8 | K11: 0.3 | M11: 3.2 | N11: 0 | Q11: 0 | T11: 0
A12: ENGINEERING CRAFT | B12: Testing | C12: Taking responsibility | D12: 1 | E12: 0.1 | G12: 1.8 | H12: 0.15 | J12: 2.4 | K12: 0.2 | M12: 2.8 | N12: 0 | Q12: 0 | T12: 0
A13: ENGINEERING CRAFT | B13: Testing | C13: Leading testing strategy | D13: 0 | E13: 0 | G13: 0 | H13: 0 | J13: 1 | K13: 0 | M13: 2.5 | N13: 0.5 | P13: 3.6 | Q13: 0.5 | S13: 4 | T13: 0.5
A14: ENGINEERING CRAFT | B14: Testing | C14: Advocating for testing | D14: 0 | E14: 0 | G14: 0 | H14: 0 | J14: 1 | K14: 0 | M14: 2.5 | N14: 0.5 | P14: 3.6 | Q14: 0.5 | S14: 4 | T14: 0.5
A15: ENGINEERING CRAFT | B15: Technical Understanding & Prioritisation | D15: =D16*E16+D17*E17+D18*E18+D19*E19 -> 1.29 | E15: 0.15 | G15: =G16*H16+G17*H17+G18*H18+G19*H19 -> 2.07 | H15: 0.15 | J15: =J16*K16+J17*K17+J18*K18+J19*K19 -> 2.46 | K15: 0.15 | M15: =M16*N16+M17*N17+M18*N18+M19*N19 -> 3.25 | N15: 0.15 | P15: =P16*Q16+P17*Q17+P18*Q18+P19*Q19 -> 3.705 | Q15: 0.15 | S15: =S16*T16+S17*T17+S18*T18+S19*T19 -> 4 | T15: 0.15
A16: ENGINEERING CRAFT | B16: Technical Understanding & Prioritisation | C16: Understanding code | D16: 1.4 | E16: 0.6 | G16: 2.2 | H16: 0.55 | J16: 2.2 | K16: 0.55 | M16: 3.4 | N16: 0.5 | P16: 3.8 | Q16: 0.5 | S16: 4 | T16: 0.5
A17: ENGINEERING CRAFT | B17: Technical Understanding & Prioritisation | C17: Technical collaboration | D17: 1.2 | E17: 0.25 | G17: 2 | H17: 0.25 | J17: 2.6 | K17: 0.25 | M17: 3.2 | N17: 0.25 | P17: 3.6 | Q17: 0.25 | S17: 4 | T17: 0.25
A18: ENGINEERING CRAFT | B18: Technical Understanding & Prioritisation | C18: Work breakdown | D18: 1 | E18: 0.1 | G18: 1.8 | H18: 0.15 | J18: 2.4 | K18: 0.15 | M18: 3 | N18: 0.15 | P18: 3.5 | Q18: 0.15 | S18: 4 | T18: 0.15
A19: ENGINEERING CRAFT | B19: Technical Understanding & Prioritisation | C19: Task prioritisation | D19: 1 | E19: 0.05 | G19: 1.8 | H19: 0.05 | J19: 2.4 | K19: 0.1 | M19: 3 | N19: 0.1 | P19: 3.8 | Q19: 0.1 | S19: 4 | T19: 0.1
A20: ENGINEERING CRAFT | B20: Software Architecture | D20: =D21*E21+D22*E22+D23*E23+D24*E24+D25*E25 -> 0.9 | E20: 0.1 | G20: =G21*H21+G22*H22+G23*H23+G24*H24+G25*H25 -> 1.45 | H20: 0.12 | J20: =J21*K21+J22*K22+J23*K23+J24*K24+J25*K25 -> 2.17 | K20: 0.15 | M20: =M21*N21+M22*N22+M23*N23+M24*N24+M25*N25 -> 2.78 | N20: 0.15 | P20: =P21*Q21+P22*Q22+P23*Q23+P24*Q24+P25*Q25 -> 3.72 | Q20: 0.15 | S20: =S21*T21+S22*T22+S23*T23+S24*T24+S25*T25 -> 4 | T20: 0.15
A21: ENGINEERING CRAFT | B21: Software Architecture | C21: Reaction to feedback | D21: 2 | E21: 0.3 | G21: 2.5 | H21: 0.25 | J21: 3 | K21: 0.2 | M21: 3.5 | N21: 0 | P21: 3.5 | Q21: 0 | S21: 4 | T21: 0
A22: ENGINEERING CRAFT | B22: Software Architecture | C22: Code | D22: 1 | E22: 0.3 | G22: 1.8 | H22: 0.25 | J22: 2.6 | K22: 0.2 | M22: 3.4 | N22: 0 | P22: 3.6 | Q22: 0 | S22: 4 | T22: 0
A23: ENGINEERING CRAFT | B23: Software Architecture | C23: Design | D23: 0 | E23: 0.2 | G23: 0.5 | H23: 0.25 | J23: 1.5 | K23: 0.3 | M23: 2.5 | N23: 0.4 | P23: 3.8 | Q23: 0.4 | S23: 4 | T23: 0.4
A24: ENGINEERING CRAFT | B24: Software Architecture | C24: Development | D24: 0 | E24: 0.2 | G24: 1 | H24: 0.25 | J24: 2 | K24: 0.3 | M24: 3 | N24: 0.4 | P24: 3.7 | Q24: 0.4 | S24: 4 | T24: 0.4
A25: ENGINEERING CRAFT | B25: Software Architecture | C25: Technical debt | D25: 0.5 | E25: 0 | G25: 1.3 | H25: 0 | J25: 2.1 | K25: 0 | M25: 2.9 | N25: 0.2 | P25: 3.6 | Q25: 0.2 | S25: 4 | T25: 0.2
A26: ENGINEERING CRAFT | B26: Security | D26: =D27*E27+D28*E28+D29*E29+D30*E30+D31*E31+D32*E32 -> 1.28 | E26: 0.1 | G26: =G27*H27+G28*H28+G29*H29+G30*H30+G31*H31+G32*H32 -> 1.995 | H26: 0.1 | J26: =J27*K27+J28*K28+J29*K29+J30*K30+J31*K31+J32*K32 -> 2.71 | K26: 0.1 | M26: =M27*N27+M28*N28+M29*N29+M30*N30+M31*N31+M32*N32 -> 3.19 | N26: 0.1 | P26: =P27*Q27+P28*Q28+P29*Q29+P30*Q30+P31*Q31+P32*Q32 -> 3.62 | Q26: 0.1 | S26: =S27*T27+S28*T28+S29*T29+S30*T30+S31*T31+S32*T32 -> 4 | T26: 0.1
A27: ENGINEERING CRAFT | B27: Security | C27: Knowledge | D27: 1.2 | E27: 0.4 | G27: 2 | H27: 0.35 | J27: 2.8 | K27: 0.3 | M27: 3.6 | N27: 0.3 | P27: 3.6 | Q27: 0.3 | S27: 4 | T27: 0.3
A28: ENGINEERING CRAFT | B28: Security | C28: User data | D28: 1.5 | E28: 0.4 | G28: 2.3 | H28: 0.35 | J28: 3.1 | K28: 0.3 | M28: 3.7 | N28: 0.3 | P28: 3.7 | Q28: 0.3 | S28: 4 | T28: 0.2
A29: ENGINEERING CRAFT | B29: Security | C29: Reporting | D29: 1 | E29: 0.2 | G29: 1.8 | H29: 0.2 | J29: 2.6 | K29: 0.2 | M29: 3.2 | N29: 0 | P29: 3.4 | Q29: 0 | S29: 4 | T29: 0.1
A30: ENGINEERING CRAFT | B30: Security | C30: Proactivity | D30: 0.5 | E30: 0 | G30: 1.3 | H30: 0.1 | J30: 2.1 | K30: 0.2 | M30: 2.9 | N30: 0 | P30: 3.5 | Q30: 0.1 | S30: 4 | T30: 0.1
A31: ENGINEERING CRAFT | B31: Security | C31: Collaboration | D31: 0.8 | E31: 0 | G31: 1.6 | H31: 0 | J31: 2.4 | K31: 0 | M31: 3 | N31: 0 | P31: 3.4 | Q31: 0.1 | S31: 4 | T31: 0.1
A32: ENGINEERING CRAFT | B32: Security | C32: Strategy | D32: 0 | E32: 0 | G32: 0.5 | H32: 0 | J32: 1.5 | K32: 0 | M32: 2.5 | N32: 0.4 | P32: 3.7 | Q32: 0.2 | S32: 4 | T32: 0.2
A33: ENGINEERING CRAFT | B33: Debugging & Monitoring | D33: =D34*E34+D35*E35+D36*E36+D37*E37+D38*E38+D39*E39 -> 1.07 | E33: 0.05 | G33: =G34*H34+G35*H35+G36*H36+G37*H37+G38*H38+G39*H39 -> 1.825 | H33: 0.08 | J33: =J34*K34+J35*K35+J36*K36+J37*K37+J38*K38+J39*K39 -> 2.525 | K33: 0.1 | M33: =M34*N34+M35*N35+M36*N36+M37*N37+M38*N38+M39*N39 -> 2.98 | N33: 0.15 | P33: =P34*Q34+P35*Q35+P36*Q36+P37*Q37+P38*Q38+P39*Q39 -> 3.64 | Q33: 0.15 | S33: =S34*T34+S35*T35+S36*T36+S37*T37+S38*T38+S39*T39 -> 4 | T33: 0.15
A34: ENGINEERING CRAFT | B34: Debugging & Monitoring | C34: Debugging | D34: 1.2 | E34: 0.6 | G34: 2 | H34: 0.55 | J34: 2.8 | K34: 0.4 | M34: 3.4 | N34: 0.3 | P34: 3.8 | Q34: 0.3 | S34: 4 | T34: 0.4
A35: ENGINEERING CRAFT | B35: Debugging & Monitoring | C35: Tools | D35: 1 | E35: 0.3 | G35: 1.8 | H35: 0.25 | J35: 2.6 | K35: 0.2 | M35: 3.2 | N35: 0 | P35: 3.4 | Q35: 0 | S35: 4 | T35: 0
A36: ENGINEERING CRAFT | B36: Debugging & Monitoring | C36: Philosophy | D36: 0.5 | E36: 0.1 | G36: 1.3 | H36: 0.15 | J36: 2.1 | K36: 0.2 | M36: 2.9 | N36: 0.2 | P36: 3.6 | Q36: 0.2 | S36: 4 | T36: 0.2
A37: ENGINEERING CRAFT | B37: Debugging & Monitoring | C37: Data | D37: 0.8 | E37: 0 | G37: 1.6 | H37: 0.05 | J37: 2.4 | K37: 0.15 | M37: 3 | N37: 0.2 | P37: 3.5 | Q37: 0.2 | S37: 4 | T37: 0.2
A38: ENGINEERING CRAFT | B38: Debugging & Monitoring | C38: Profiling | D38: 0.5 | E38: 0 | G38: 1.3 | H38: 0 | J38: 2.1 | K38: 0.05 | M38: 2.9 | N38: 0.2 | P38: 3.7 | Q38: 0.2 | S38: 4 | T38: 0.2
A39: ENGINEERING CRAFT | B39: Debugging & Monitoring | C39: Mentoring | D39: 0 | E39: 0 | G39: 0 | H39: 0 | J39: 1 | K39: 0 | M39: 2 | N39: 0.1 | P39: 3.4 | Q39: 0.1 | S39: 4 | T39: 0
A40: ENGINEERING CRAFT | E40: =E4+E9+E15+E20+E26+E33 -> 1 | H40: =H4+H9+H15+H20+H26+H33 -> 1 | K40: =K4+K9+K15+K20+K26+K33 -> 1 | N40: =N4+N9+N15+N20+N26+N33 -> 1 | Q40: =Q4+Q9+Q15+Q20+Q26+Q33 -> 1 | T40: =T4+T9+T15+T20+T26+T33 -> 1
A41: SOFT SKILLS | D41: =D42*E42+D47*E47+D52*E52+D56*E56+D61*E61 -> 1.2286 | E41: 0.25 | G41: =G42*H42+G47*H47+G52*H52+G56*H56+G61*H61 -> 1.7285 | H41: 0.3 | J41: =J42*K42+J47*K47+J52*K52+J56*K56+J61*K61 -> 2.264 | K41: 0.3 | M41: =M42*N42+M47*N47+M52*N52+M56*N56+M61*N61 -> 2.807 | N41: 0.4 | P41: =P42*Q42+P47*Q47+P52*Q52+P56*Q56+P61*Q61 -> 3.348 | Q41: 0.4 | S41: =S42*T42+S47*T47+S52*T52+S56*T56+S61*T61 -> 3.848 | T41: 0.4
A42: SOFT SKILLS | B42: Empathy & Humility | D42: =D43*E43+D44*E44+D45*E45+D46*E46 -> 0.85 | E42: 0.4 | G42: =G43*H43+G44*H44+G45*H45+G46*H46 -> 1.53 | H42: 0.4 | J42: =J43*K43+J44*K44+J45*K45+J46*K46 -> 2.31 | K42: 0.4 | M42: =M43*N43+M44*N44+M45*N45+M46*N46 -> 3 | N42: 0.4 | P42: =P43*Q43+P44*Q44+P45*Q45+P46*Q46 -> 3.62 | Q42: 0.4 | S42: =S43*T43+S44*T44+S45*T45+S46*T46 -> 4 | T42: 0.4
A43: SOFT SKILLS | B43: Empathy & Humility | C43: Credit and blame | D43: 1 | E43: 0.3 | G43: 1.8 | H43: 0.3 | J43: 2.6 | K43: 0.3 | M43: 3.2 | N43: 0.3 | P43: 3.8 | Q43: 0.3 | S43: 4 | T43: 0.3
A44: SOFT SKILLS | B44: Empathy & Humility | C44: Understanding others | D44: 1.5 | E44: 0.3 | G44: 2.1 | H44: 0.3 | J44: 2.7 | K44: 0.3 | M44: 3.2 | N44: 0.3 | P44: 3.6 | Q44: 0.3 | S44: 4 | T44: 0.3
A45: SOFT SKILLS | B45: Empathy & Humility | C45: Mediation and facilitation | D45: 0.5 | E45: 0.2 | G45: 1.3 | H45: 0.2 | J45: 2.1 | K45: 0.2 | M45: 2.9 | N45: 0.2 | P45: 3.5 | Q45: 0.2 | S45: 4 | T45: 0.2
A46: SOFT SKILLS | B46: Empathy & Humility | C46: Mentoring | D46: 0 | E46: 0.2 | G46: 0.5 | H46: 0.2 | J46: 1.5 | K46: 0.2 | M46: 2.5 | N46: 0.2 | P46: 3.5 | Q46: 0.2 | S46: 4 | T46: 0.2
A47: SOFT SKILLS | B47: Communication | D47: =D48*E48+D49*E49+D50*E50+D51*E51 -> 1.25 | E47: 0.3 | G47: =G48*H48+G49*H49+G50*H50+G51*H51 -> 1.6 | H47: 0.25 | J47: =J48*K48+J49*K49+J50*K50+J51*K51 -> 1.96 | K47: 0.2 | M47: =M48*N48+M49*N49+M50*N50+M51*N51 -> 2.39 | N47: 0.2 | P47: =P48*Q48+P49*Q49+P50*Q50+P51*Q51 -> 2.84 | Q47: 0.2 | S47: =S48*T48+S49*T49+S50*T50+S51*T51 -> 3.44 | T47: 0.2
A48: SOFT SKILLS | B48: Communication | C48: Keeping people informed | D48: 1.2 | E48: 0.5 | G48: 1.6 | H48: 0.5 | J48: 2 | K48: 0.5 | M48: 2.4 | N48: 0.5 | P48: 3.2 | Q48: 0.5 | S48: 4 | T48: 0.5
A49: SOFT SKILLS | B49: Communication | C49: Looking for feedback | D49: 2 | E49: 0.3 | G49: 2.4 | H49: 0.25 | J49: 2.8 | K49: 0.2 | M49: 3.2 | N49: 0.2 | P49: 3.4 | Q49: 0.2 | S49: 4 | T49: 0.2
A50: SOFT SKILLS | B50: Communication | C50: Delivering bad news | D50: 0.5 | E50: 0.1 | G50: 1 | H50: 0.15 | J50: 1.5 | K50: 0.2 | M50: 2 | N50: 0.2 | P50: 2.8 | Q50: 0.1 | S50: 3.2 | T50: 0.1
A51: SOFT SKILLS | B51: Communication | C51: Mentoring communicators | D51: 0 | E51: 0.1 | G51: 0.5 | H51: 0.1 | J51: 1 | K51: 0.1 | M51: 1.5 | N51: 0.1 | P51: 2.8 | Q51: 0.1 | S51: 3.2 | T51: 0.1
A52: SOFT SKILLS | B52: Initiative | D52: =D53*E53+D54*E54+D55*E55 -> 1.85 | E52: 0.2 | G52: =G53*H53+G54*H54+G55*H55 -> 2.15 | H52: 0.2 | J52: =J53*K53+J54*K54+J55*K55 -> 2.45 | K52: 0.2 | M52: =M53*N53+M54*N54+M55*N55 -> 2.8 | N52: 0.2 | P52: =P53*Q53+P54*Q54+P55*Q55 -> 3.25 | Q52: 0.2 | S52: =S53*T53+S54*T54+S55*T55 -> 3.9 | T52: 0.2
A53: SOFT SKILLS | B53: Initiative | C53: Can-do attitude | D53: 2 | E53: 0.6 | G53: 2.4 | H53: 0.55 | J53: 2.8 | K53: 0.5 | M53: 3.2 | N53: 0.5 | P53: 3.4 | Q53: 0.5 | S53: 4 | T53: 0.5
A54: SOFT SKILLS | B54: Initiative | C54: Pro-activity in seeking help | D54: 2 | E54: 0.25 | G54: 2.2 | H54: 0.25 | J54: 2.4 | K54: 0.25 | M54: 2.6 | N54: 0.25 | P54: 3 | Q54: 0.25 | S54: 3.6 | T54: 0.25
A55: SOFT SKILLS | B55: Initiative | C55: Follow through | D55: 1 | E55: 0.15 | G55: 1.4 | H55: 0.2 | J55: 1.8 | K55: 0.25 | M55: 2.2 | N55: 0.25 | P55: 3.2 | Q55: 0.25 | S55: 4 | T55: 0.25
A56: SOFT SKILLS | B56: Objectivity & Adaptability | D56: =D57*E57+D58*E58+D59*E59+D60*E60 -> 1.545 | E56: 0.08 | G56: =G57*H57+G58*H58+G59*H59+G60*H60 -> 2.165 | H56: 0.1 | J56: =J57*K57+J58*K58+J59*K59+J60*K60 -> 2.78 | K56: 0.1 | M56: =M57*N57+M58*N58+M59*N59+M60*N60 -> 3.29 | N56: 0.1 | P56: =P57*Q57+P58*Q58+P59*Q59+P60*Q60 -> 3.62 | Q56: 0.1 | S56: =S57*T57+S58*T58+S59*T59+S60*T60 -> 4 | T56: 0.1
A57: SOFT SKILLS | B57: Objectivity & Adaptability | C57: Efficient decision-making | D57: 1 | E57: 0.5 | G57: 1.8 | H57: 0.5 | J57: 2.6 | K57: 0.5 | M57: 3.2 | N57: 0.5 | P57: 3.6 | Q57: 0.5 | S57: 4 | T57: 0.5
A58: SOFT SKILLS | B58: Objectivity & Adaptability | C58: Self improvement | D58: 2.5 | E58: 0.3 | G58: 3 | H58: 0.25 | J58: 3.5 | K58: 0.2 | M58: 3.8 | N58: 0.2 | P58: 3.8 | Q58: 0.2 | S58: 4 | T58: 0.2
A59: SOFT SKILLS | B59: Objectivity & Adaptability | C59: Objectivity | D59: 1.5 | E59: 0.15 | G59: 2.1 | H59: 0.2 | J59: 2.7 | K59: 0.2 | M59: 3.2 | N59: 0.2 | P59: 3.6 | Q59: 0.2 | S59: 4 | T59: 0.2
A60: SOFT SKILLS | B60: Objectivity & Adaptability | C60: Time management | D60: 1.4 | E60: 0.05 | G60: 1.9 | H60: 0.05 | J60: 2.4 | K60: 0.1 | M60: 2.9 | N60: 0.1 | P60: 3.4 | Q60: 0.1 | S60: 4 | T60: 0.1
A61: SOFT SKILLS | B61: Business Acumen | D61: =D62*E62 -> 1 | E61: 0.02 | G61: =G62*H62 -> 1.4 | H61: 0.05 | J61: =J62*K62 -> 1.8 | K61: 0.1 | M61: =M62*N62 -> 2.4 | N61: 0.1 | P61: =P62*Q62 -> 3.2 | Q61: 0.1 | S61: =S62*T62 -> 3.8 | T61: 0.1
A62: SOFT SKILLS | B62: Business Acumen | C62: Understanding level | D62: 1 | E62: 1 | G62: 1.4 | H62: 1 | J62: 1.8 | K62: 1 | M62: 2.4 | N62: 1 | P62: 3.2 | Q62: 1 | S62: 3.8 | T62: 1
A63: SOFT SKILLS | E63: =E42+E47+E52+E56+E61 -> 1 | H63: =H42+H47+H52+H56+H61 -> 1 | K63: =K42+K47+K52+K56+K61 -> 1 | N63: =N42+N47+N52+N56+N61 -> 1 | Q63: =Q42+Q47+Q52+Q56+Q61 -> 1 | T63: =T42+T47+T52+T56+T61 -> 1
A64: LEADERSHIP | D64: =D65*E65+D69*E69+D74*E74+D79*E79+D84*E84 -> 0.529 | E64: 0.05 | G64: =G65*H65+G69*H69+G74*H74+G79*H79+G84*H84 -> 0.933 | H64: 0.05 | J64: =J65*K65+J69*K69+J74*K74+J79*K79+J84*K84 -> 1.2755 | K64: 0.1 | M64: =M65*N65+M69*N69+M74*N74+M79*N79+M84*N84 -> 1.598 | N64: 0.2 | P64: =P65*Q65+P69*Q69+P74*Q74+P79*Q79+P84*Q84 -> 2.598 | Q64: 0.2 | S64: =S65*T65+S69*T69+S74*T74+S79*T79+S84*T84 -> 3.5 | T64: 0.2
A65: LEADERSHIP | B65: Hiring and Org Design | D65: =D66*E66+D67*E67+D68*E68 -> 0 | E65: 0.2 | G65: =G66*H66+G67*H67+G68*H68 -> 0.2 | H65: 0.2 | J65: =J66*K66+J67*K67+J68*K68 -> 0.48 | K65: 0.3 | M65: =M66*N66+M67*N67+M68*N68 -> 0.95 | N65: 0.4 | P65: =P66*Q66+P67*Q67+P68*Q68 -> 2.24 | Q65: 0.4 | S65: =S66*T66+S67*T67+S68*T68 -> 3.4 | T65: 0.4
A66: LEADERSHIP | B66: Hiring and Org Design | C66: Deploying Teams | D66: 0 | E66: 0.4 | G66: 0 | H66: 0.4 | J66: 0.2 | K66: 0.4 | M66: 0.8 | N66: 0.5 | P66: 2.4 | Q66: 0.5 | S66: 3.6 | T66: 0.5
A67: LEADERSHIP | B67: Hiring and Org Design | C67: Employer Brand | D67: 0 | E67: 0.4 | G67: 0.5 | H67: 0.4 | J67: 1 | K67: 0.4 | M67: 1.5 | N67: 0.3 | P67: 2.8 | Q67: 0.3 | S67: 4 | T67: 0.3
A68: LEADERSHIP | B68: Hiring and Org Design | C68: Hiring | D68: 0 | E68: 0.2 | G68: 0 | H68: 0.2 | J68: 0 | K68: 0.2 | M68: 0.5 | N68: 0.2 | P68: 1 | Q68: 0.2 | S68: 2 | T68: 0.2
A69: LEADERSHIP | B69: Stakeholder Management | D69: =D70*E70+D71*E71+D72*E72+D73*E73 -> 0.73 | E69: 0.3 | G69: =G70*H70+G71*H71+G72*H72+G73*H73 -> 1.35 | H69: 0.3 | J69: =J70*K70+J71*K71+J72*K72+J73*K73 -> 1.97 | K69: 0.3 | M69: =M70*N70+M71*N71+M72*N72+M73*N73 -> 2.74 | N69: 0.2 | P69: =P70*Q70+P71*Q71+P72*Q72+P73*Q73 -> 3.6 | Q69: 0.2 | S69: =S70*T70+S71*T71+S72*T72+S73*T73 -> 4 | T69: 0.2
A70: LEADERSHIP | B70: Stakeholder Management | C70: Managing Goals and Expectations | D70: 0.5 | E70: 0.4 | G70: 1.1 | H70: 0.4 | J70: 1.7 | K70: 0.4 | M70: 2.5 | N70: 0.5 | P70: 3.6 | Q70: 0.5 | S70: 4 | T70: 0.5
A71: LEADERSHIP | B71: Stakeholder Management | C71: Foresight | D71: 0.8 | E71: 0.3 | G71: 1.4 | H71: 0.3 | J71: 2 | K71: 0.3 | M71: 2.8 | N71: 0.2 | P71: 3.4 | Q71: 0.2 | S71: 4 | T71: 0.2
A72: LEADERSHIP | B72: Stakeholder Management | C72: Engendering Trust | D72: 1.2 | E72: 0.2 | G72: 1.8 | H72: 0.2 | J72: 2.4 | K72: 0.2 | M72: 3.2 | N72: 0.2 | P72: 3.8 | Q72: 0.2 | S72: 4 | T72: 0.2
A73: LEADERSHIP | B73: Stakeholder Management | C73: Protecting the Team | D73: 0.5 | E73: 0.1 | G73: 1.3 | H73: 0.1 | J73: 2.1 | K73: 0.1 | M73: 2.9 | N73: 0.1 | P73: 3.6 | Q73: 0.1 | S73: 4 | T73: 0.1
A74: LEADERSHIP | B74: Team Leadership | D74: =D75*E75+D76*E76+D77*E77+D78*E78 -> 0.85 | E74: 0.2 | G74: =G75*H75+G76*H76+G77*H77+G78*H78 -> 1.22 | H74: 0.2 | J74: =J75*K75+J76*K76+J77*K77+J78*K78 -> 1.59 | K74: 0.2 | M74: =M75*N75+M76*N76+M77*N77+M78*N78 -> 2 | N74: 0.1 | P74: =P75*Q75+P76*Q76+P77*Q77+P78*Q78 -> 2.6 | Q74: 0.1 | S74: =S75*T75+S76*T76+S77*T77+S78*T78 -> 3.54 | T74: 0.1
A75: LEADERSHIP | B75: Team Leadership | C75: Putting the Team first | D75: 1 | E75: 0.5 | G75: 1.5 | H75: 0.5 | J75: 2 | K75: 0.5 | M75: 2.5 | N75: 0.5 | P75: 3 | Q75: 0.5 | S75: 4 | T75: 0.5
A76: LEADERSHIP | B76: Team Leadership | C76: Difficult Conversations | D76: 0 | E76: 0.2 | G76: 0.2 | H76: 0.2 | J76: 0.4 | K76: 0.2 | M76: 0.8 | N76: 0.2 | P76: 2 | Q76: 0.2 | S76: 3 | T76: 0.2
A77: LEADERSHIP | B77: Team Leadership | C77: Reliability | D77: 1 | E77: 0.2 | G77: 1.3 | H77: 0.2 | J77: 1.6 | K77: 0.2 | M77: 1.9 | N77: 0.2 | P77: 2.4 | Q77: 0.2 | S77: 3.2 | T77: 0.2
A78: LEADERSHIP | B78: Team Leadership | C78: Vulnerability | D78: 1.5 | E78: 0.1 | G78: 1.7 | H78: 0.1 | J78: 1.9 | K78: 0.1 | M78: 2.1 | N78: 0.1 | P78: 2.2 | Q78: 0.1 | S78: 3 | T78: 0.1
A79: LEADERSHIP | B79: Developing Others | D79: =D80*E80+D81*E81+D82*E82+D83*E83 -> 0.15 | E79: 0.2 | G79: =G80*H80+G81*H81+G82*H82+G83*H83 -> 0.53 | H79: 0.2 | J79: =J80*K80+J81*K81+J82*K82+J83*K83 -> 0.93 | K79: 0.15 | M79: =M80*N80+M81*N81+M82*N82+M83*N83 -> 1.47 | N79: 0.2 | P79: =P80*Q80+P81*Q81+P82*Q82+P83*Q83 -> 2.42 | Q79: 0.2 | S79: =S80*T80+S81*T81+S82*T82+S83*T83 -> 3.28 | T79: 0.2
A80: LEADERSHIP | B80: Developing Others | C80: Identifying strengths | D80: 0 | E80: 0.3 | G80: 0.4 | H80: 0.3 | J80: 0.8 | K80: 0.3 | M80: 1.2 | N80: 0.3 | P80: 2.6 | Q80: 0.3 | S80: 3.6 | T80: 0.3
A81: LEADERSHIP | B81: Developing Others | C81: Supporting team growth | D81: 0 | E81: 0.4 | G81: 0.4 | H81: 0.4 | J81: 0.8 | K81: 0.4 | M81: 1.6 | N81: 0.4 | P81: 2.4 | Q81: 0.4 | S81: 3.2 | T81: 0.4
A82: LEADERSHIP | B82: Developing Others | C82: Investing in process | D82: 0.5 | E82: 0.2 | G82: 0.9 | H82: 0.2 | J82: 1.3 | K82: 0.2 | M82: 1.7 | N82: 0.1 | P82: 2.4 | Q82: 0.1 | S82: 3.2 | T82: 0.1
A83: LEADERSHIP | B83: Developing Others | C83: Feedback on work | D83: 0.5 | E83: 0.1 | G83: 0.7 | H83: 0.1 | J83: 1.1 | K83: 0.1 | M83: 1.5 | N83: 0.2 | P83: 2.2 | Q83: 0.2 | S83: 3 | T83: 0.2
A84: LEADERSHIP | B84: Culture & Togetherness | D84: =D85*E85+D86*E86+D87*E87 -> 1.1 | E84: 0.1 | G84: =G85*H85+G86*H86+G87*H87 -> 1.38 | H84: 0.1 | J84: =J85*K85+J86*K86+J87*K87 -> 1.66 | K84: 0.05 | M84: =M85*N85+M86*N86+M87*N87 -> 1.76 | N84: 0.1 | P84: =P85*Q85+P86*Q86+P87*Q87 -> 2.38 | Q84: 0.1 | S84: =S85*T85+S86*T86+S87*T87 -> 3.3 | T84: 0.1
A85: LEADERSHIP | B85: Culture & Togetherness | C85: Setting an Example | D85: 1.5 | E85: 0.5 | G85: 1.8 | H85: 0.5 | J85: 2.1 | K85: 0.5 | M85: 2.4 | N85: 0.3 | P85: 2.8 | Q85: 0.3 | S85: 4 | T85: 0.3
A86: LEADERSHIP | B86: Culture & Togetherness | C86: Encouraging diverse opinions | D86: 0.5 | E86: 0.3 | G86: 0.8 | H86: 0.3 | J86: 1.1 | K86: 0.3 | M86: 1.4 | N86: 0.4 | P86: 2.2 | Q86: 0.4 | S86: 3 | T86: 0.4
A87: LEADERSHIP | B87: Culture & Togetherness | C87: Developing personal relationships | D87: 1 | E87: 0.2 | G87: 1.2 | H87: 0.2 | J87: 1.4 | K87: 0.2 | M87: 1.6 | N87: 0.3 | P87: 2.2 | Q87: 0.3 | S87: 3 | T87: 0.3
A88: LEADERSHIP | E88: =E65+E69+E74+E79+E84 -> 1 | H88: =H65+H69+H74+H79+H84 -> 1 | K88: =K65+K69+K74+K79+K84 -> 1 | N88: =N65+N69+N74+N79+N84 -> 1 | Q88: =Q65+Q69+Q74+Q79+Q84 -> 1 | T88: =T65+T69+T74+T79+T84 -> 1
C90: Role Model Rating | D90: =D64*E64+D41*E41+D3*E3 -> 1.2156 | E90: =E3+E41+E64 -> 1 | G90: =G64*H64+G41*H41+G3*H3 -> 1.844075 | H90: =H3+H41+H64 -> 1 | J90: =J64*K64+J41*K41+J3*K3 -> 2.32745 | K90: =K3+K41+K64 -> 1 | M90: =M64*N64+M41*N41+M3*N3 -> 2.6386 | N90: =N3+N41+N64 -> 1 | P90: =P64*Q64+P41*Q41+P3*Q3 -> 3.3167 | Q90: =Q3+Q41+Q64 -> 1 | S90: =S64*T64+S41*T41+S3*T3 -> 3.8392 | T90: =T3+T41+T64 -> 1

Sheet raw_weights
A1: key | B1: Order | C1: Level | D1: Section | E1: Subsection | F1: Criteria | G1: Role model Rating | H1: Weights | I1: Description
A2: =TRIM(C2&D2&E2&F2) -> Junior DeveloperENGINEERING CRAFT | B2: 0 | C2: Junior Developer | D2: =weights_editor!A3 -> ENGINEERING CRAFT | E2: =weights_editor!B3 | F2: =weights_editor!C3 | G2: =weights_editor!D3 -> 1.26 | H2: =weights_editor!E3 -> 0.7
A3: =C3&D3&E3&F3 -> Junior DeveloperENGINEERING CRAFTWriting Code | B3: 1 | C3: Junior Developer | D3: =weights_editor!A4 -> ENGINEERING CRAFT | E3: =weights_editor!B4 -> Writing Code | F3: =weights_editor!C4 | G3: =weights_editor!D4 -> 1.2 | H3: =weights_editor!E4 -> 0.45 | I3: The ability to contribute high quality code to production environments. Is able to consistently write testable, readable code across larger more complex projects.
A4: =C4&D4&E4&F4 -> Junior DeveloperENGINEERING CRAFTWriting CodeQuality | B4: 2 | C4: Junior Developer | D4: =weights_editor!A5 -> ENGINEERING CRAFT | E4: =weights_editor!B5 -> Writing Code | F4: =weights_editor!C5 -> Quality | G4: =weights_editor!D5 -> 1.2 | H4: =weights_editor!E5 -> 0.5 | I4: Your code has always followed correct convention, requiring only minor improvements. You've made trade-offs knowingly.
A5: =C5&D5&E5&F5 -> Junior DeveloperENGINEERING CRAFTWriting CodeDocumentation | B5: 3 | C5: Junior Developer | D5: =weights_editor!A6 -> ENGINEERING CRAFT | E5: =weights_editor!B6 -> Writing Code | F5: =weights_editor!C6 -> Documentation | G5: =weights_editor!D6 -> 1 | H5: =weights_editor!E6 -> 0.25 | I5: You've regularly documented your code and looked to improve documentation elsewhere.
A6: =C6&D6&E6&F6 -> Junior DeveloperENGINEERING CRAFTWriting CodeLanguage | B6: 4 | C6: Junior Developer | D6: =weights_editor!A7 -> ENGINEERING CRAFT | E6: =weights_editor!B7 -> Writing Code | F6: =weights_editor!C7 -> Language | G6: =weights_editor!D7 -> 1.4 | H6: =weights_editor!E7 -> 0.25 | I6: You're committing quality code in at least one language and have a working understanding of other languages your team needs.
A7: =C7&D7&E7&F7 -> Junior DeveloperENGINEERING CRAFTWriting CodeMentoring | B7: 5 | C7: Junior Developer | D7: =weights_editor!A8 -> ENGINEERING CRAFT | E7: =weights_editor!B8 -> Writing Code | F7: =weights_editor!C8 -> Mentoring | G7: =weights_editor!D8 -> 0 | H7: =weights_editor!E8 -> 0 | I7: N/A
A8: =C8&D8&E8&F8 -> Junior DeveloperENGINEERING CRAFTTesting | B8: 6 | C8: Junior Developer | D8: =weights_editor!A9 -> ENGINEERING CRAFT | E8: =weights_editor!B9 -> Testing | F8: =weights_editor!C9 | G8: =weights_editor!D9 -> 1.7 | H8: =weights_editor!E9 -> 0.15 | I8: The ability to understand and implement great testing practices. Understands how to test code, and the valuable role that testing plays.
A9: =C9&D9&E9&F9 -> Junior DeveloperENGINEERING CRAFTTestingTesting your code | B9: 7 | C9: Junior Developer | D9: =weights_editor!A10 -> ENGINEERING CRAFT | E9: =weights_editor!B10 -> Testing | F9: =weights_editor!C10 -> Testing your code | G9: =weights_editor!D10 -> 2 | H9: =weights_editor!E10 -> 0.7 | I9: You consistently write solid unit tests, sometimes with help from more senior engineers.
A10: =C10&D10&E10&F10 -> Junior DeveloperENGINEERING CRAFTTestingImproving coverage | B10: 8 | C10: Junior Developer | D10: =weights_editor!A11 -> ENGINEERING CRAFT | E10: =weights_editor!B11 -> Testing | F10: =weights_editor!C11 -> Improving coverage | G10: =weights_editor!D11 -> 1 | H10: =weights_editor!E11 -> 0.2 | I10: You've spotted small areas of low test coverage and patched them.
A11: =C11&D11&E11&F11 -> Junior DeveloperENGINEERING CRAFTTestingTaking responsibility | B11: 9 | C11: Junior Developer | D11: =weights_editor!A12 -> ENGINEERING CRAFT | E11: =weights_editor!B12 -> Testing | F11: =weights_editor!C12 -> Taking responsibility | G11: =weights_editor!D12 -> 1 | H11: =weights_editor!E12 -> 0.1 | I11: You've consistently ensured that your code passes tests before creating or merging pull requests
A12: =C12&D12&E12&F12 -> Junior DeveloperENGINEERING CRAFTTestingLeading testing strategy | B12: 10 | C12: Junior Developer | D12: =weights_editor!A13 -> ENGINEERING CRAFT | E12: =weights_editor!B13 -> Testing | F12: =weights_editor!C13 -> Leading testing strategy | G12: =weights_editor!D13 -> 0 | H12: =weights_editor!E13 -> 0 | I12: N/A
A13: =C13&D13&E13&F13 -> Junior DeveloperENGINEERING CRAFTTestingAdvocating for testing | B13: 11 | C13: Junior Developer | D13: =weights_editor!A14 -> ENGINEERING CRAFT | E13: =weights_editor!B14 -> Testing | F13: =weights_editor!C14 -> Advocating for testing | G13: =weights_editor!D14 -> 0 | H13: =weights_editor!E14 -> 0 | I13: N/A
A14: =C14&D14&E14&F14 -> Junior DeveloperENGINEERING CRAFTTechnical Understanding & Prioritisation | B14: 12 | C14: Junior Developer | D14: =weights_editor!A15 -> ENGINEERING CRAFT | E14: =weights_editor!B15 -> Technical Understanding & Prioritisation | F14: =weights_editor!C15 | G14: =weights_editor!D15 -> 1.29 | H14: =weights_editor!E15 -> 0.15 | I14: The ability to develop technical understanding and use this to prioritise tasks appropriately. Shows some confidence in technical understanding including the importance of prioritisation.
... A38: =C38&D38&E38&F38 -> Junior DeveloperENGINEERING CRAFTDebugging & MonitoringMentoring | B38: 36 | C38: Junior Developer | D38: =weights_editor!A39 -> ENGINEERING CRAFT | E38: =weights_editor!B39 -> Debugging & Monitoring | F38: =weights_editor!C39 -> Mentoring | G38: =weights_editor!D39 -> 0 | H38: =weights_editor!E39 -> 0 | I38: N/A
A39: =C39&D39&E39&F39 -> Junior DeveloperSOFT SKILLS | B39: 37 | C39: Junior Developer | D39: =weights_editor!A41 -> SOFT SKILLS | E39: =weights_editor!B41 | F39: =weights_editor!C41 | G39: =weights_editor!D41 -> 1.2286 | H39: =weights_editor!E41 -> 0.25
A40: =C40&D40&E40&F40 -> Junior DeveloperSOFT SKILLSEmpathy & Humility | B40: 38 | C40: Junior Developer | D40: =weights_editor!A42 -> SOFT SKILLS | E40: =weights_editor!B42 -> Empathy & Humility | F40: =weights_editor!C42 | G40: =weights_editor!D42 -> 0.85 | H40: =weights_editor!E42 -> 0.4 | I40: The ability to share someone else's feelings or experiences by imagining what it would be like to be in that person's situation. Constantly pushes for a better understanding of the needs and perspectives of those outside their own viewpoint.
A41: =C41&D41&E41&F41 -> Junior DeveloperSOFT SKILLSEmpathy & HumilityCredit and blame | B41: 39 | C41: Junior Developer | D41: =weights_editor!A43 -> SOFT SKILLS | E41: =weights_editor!B43 -> Empathy & Humility | F41: =weights_editor!C43 -> Credit and blame | G41: =weights_editor!D43 -> 1 | H41: =weights_editor!E43 -> 0.3 | I41: You actively look to ensure praise is shared fairly when given to you. If someone else is blamed for your mistake, you own up.
A42: =C42&D42&E42&F42 -> Junior DeveloperSOFT SKILLSEmpathy & HumilityUnderstanding others | B42: 40 | C42: Junior Developer | D42: =weights_editor!A44 -> SOFT SKILLS | E42: =weights_editor!B44 -> Empathy & Humility | F42: =weights_editor!C44 -> Understanding others | G42: =weights_editor!D44 -> 1.5 | H42: =weights_editor!E44 -> 0.3 | I42: You regularly and actively ask others for their opinions with the goal of better understanding where they're coming from.
A43: =C43&D43&E43&F43 -> Junior DeveloperSOFT SKILLSEmpathy & HumilityMediation and facilitation | B43: 41 | C43: Junior Developer | D43: =weights_editor!A45 -> SOFT SKILLS | E43: =weights_editor!B45 -> Empathy & Humility | F43: =weights_editor!C45 -> Mediation and facilitation | G43: =weights_editor!D45 -> 0.5 | H43: =weights_editor!E45 -> 0.2 | I43: You have de-escalated disagreements amongst your peers, looking for common ground.
A44: =C44&D44&E44&F44 -> Junior DeveloperSOFT SKILLSEmpathy & HumilityMentoring | B44: 42 | C44: Junior Developer | D44: =weights_editor!A46 -> SOFT SKILLS | E44: =weights_editor!B46 -> Empathy & Humility | F44: =weights_editor!C46 -> Mentoring | G44: =weights_editor!D46 -> 0 | H44: =weights_editor!E46 -> 0.2 | I44: You've proactively developed at least one informal mentoring relationship through your ability to understand a peer or subordinate.
A45: =C45&D45&E45&F45 -> Junior DeveloperSOFT SKILLSCommunication | B45: 43 | C45: Junior Developer | D45: =weights_editor!A47 -> SOFT SKILLS | E45: =weights_editor!B47 -> Communication | F45: =weights_editor!C47 | G45: =weights_editor!D47 -> 1.25 | H45: =weights_editor!E47 -> 0.3 | I45: The ability to communicate well with those around you with sensitivity to timeliness, medium, brevity and tone. Communicates with wider team, feeds back on communication of others.
A46: =C46&D46&E46&F46 -> Junior DeveloperSOFT SKILLSCommunicationKeeping people informed | B46: 44 | C46: Junior Developer | D46: =weights_editor!A48 -> SOFT SKILLS | E46: =weights_editor!B48 -> Communication | F46: =weights_editor!C48 -> Keeping people informed | G46: =weights_editor!D48 -> 1.2 | H46: =weights_editor!E48 -> 0.5 | I46: You communicate work updates from your peers across your wider team, and respond to feedback in a timely manner.
A47: =C47&D47&E47&F47 -> Junior DeveloperSOFT SKILLSCommunicationLooking for feedback | B47: 45 | C47: Junior Developer | D47: =weights_editor!A49 -> SOFT SKILLS | E47: =weights_editor!B49 -> Communication | F47: =weights_editor!C49 -> Looking for feedback | G47: =weights_editor!D49 -> 2 | H47: =weights_editor!E49 -> 0.3 | I47: You consistently ask for critique on your thinking from a wider group, and inform the group which elements you're incorporating into your work.
A48: =C48&D48&E48&F48 -> Junior DeveloperSOFT SKILLSCommunicationDelivering bad news | B48: 46 | C48: Junior Developer | D48: =weights_editor!A50 -> SOFT SKILLS | E48: =weights_editor!B50 -> Communication | F48: =weights_editor!C50 -> Delivering bad news | G48: =weights_editor!D50 -> 0.5 | H48: =weights_editor!E50 -> 0.1 | I48: You recognise when you need help from outside your immediate peers and asked for it effectively.
A49: =C49&D49&E49&F49 -> Junior DeveloperSOFT SKILLSCommunicationMentoring communicators | B49: 47 | C49: Junior Developer | D49: =weights_editor!A51 -> SOFT SKILLS | E49: =weights_editor!B51 -> Communication | F49: =weights_editor!C51 -> Mentoring communicators | G49: =weights_editor!D51 -> 0 | H49: =weights_editor!E51 -> 0.1 | I49: You are able to unpick the communication of others around you and offer advice and feedback.
A50: =C50&D50&E50&F50 -> Junior DeveloperSOFT SKILLSInitiative | B50: 48 | C50: Junior Developer | D50: =weights_editor!A52 -> SOFT SKILLS | E50: =weights_editor!B52 -> Initiative | F50: =weights_editor!C52 | G50: =weights_editor!D52 -> 1.85 | H50: =weights_editor!E52 -> 0.2 | I50: The ability to use your judgment to make decisions and do things without needing to be told what to do. Doesn't wait to be asked. Open minded about their own skillset.
A51: =C51&D51&E51&F51 -> Junior DeveloperSOFT SKILLSInitiativeCan-do attitude | B51: 49 | C51: Junior Developer | D51: =weights_editor!A53 -> SOFT SKILLS | E51: =weights_editor!B53 -> Initiative | F51: =weights_editor!C53 -> Can-do attitude | G51: =weights_editor!D53 -> 2 | H51: =weights_editor!E53 -> 0.6 | I51: You repeatedly demonstrate a positive attitude when given new projects.
... A58: =C58&D58&E58&F58 -> Junior DeveloperSOFT SKILLSObjectivity & AdaptabilityTime management | B58: 56 | C58: Junior Developer | D58: =weights_editor!A60 -> SOFT SKILLS | E58: =weights_editor!B60 -> Objectivity & Adaptability | F58: =weights_editor!C60 -> Time management | G58: =weights_editor!D60 -> 1.4 | H58: =weights_editor!E60 -> 0.05 | I58: You look to reduce or change the scope of your work to meet a timeline or criteria not set by you.
A59: =C59&D59&E59&F59 -> Junior DeveloperSOFT SKILLSBusiness Acumen | B59: 57 | C59: Junior Developer | D59: =weights_editor!A61 -> SOFT SKILLS | E59: =weights_editor!B61 -> Business Acumen | F59: =weights_editor!C61 | G59: =weights_editor!D61 -> 1 | H59: =weights_editor!E61 -> 0.02
A60: =C60&D60&E60&F60 -> Junior DeveloperSOFT SKILLSBusiness AcumenUnderstanding level | B60: 58 | C60: Junior Developer | D60: =weights_editor!A62 -> SOFT SKILLS | E60: =weights_editor!B62 -> Business Acumen | F60: =weights_editor!C62 -> Understanding level | G60: =weights_editor!D62 -> 1 | H60: =weights_editor!E62 -> 1 | I60: Has a basic understanding of their team's domain and related marketplace.
A61: =C61&D61&E61&F61 -> Junior DeveloperLEADERSHIP | B61: 59 | C61: Junior Developer | D61: =weights_editor!A64 -> LEADERSHIP | E61: =weights_editor!B64 | F61: =weights_editor!C64 | G61: =weights_editor!D64 -> 0.529 | H61: =weights_editor!E64 -> 0.05
A62: =C62&D62&E62&F62 -> Junior DeveloperLEADERSHIPHiring and Org Design | B62: 60 | C62: Junior Developer | D62: =weights_editor!A65 -> LEADERSHIP | E62: =weights_editor!B65 -> Hiring and Org Design | F62: =weights_editor!C65 | G62: =weights_editor!D65 -> 0 | H62: =weights_editor!E65 -> 0.2 | I62: The ability to understand the needs of the business and ensure that your team can meet them. A competent interviewer. Able to follow a structured hiring process, and make a decision.
A63: =C63&D63&E63&F63 -> Junior DeveloperLEADERSHIPHiring and Org DesignDeploying Teams | B63: 61 | C63: Junior Developer | D63: =weights_editor!A66 -> LEADERSHIP | E63: =weights_editor!B66 -> Hiring and Org Design | F63: =weights_editor!C66 -> Deploying Teams | G63: =weights_editor!D66 -> 0 | H63: =weights_editor!E66 -> 0.4 | I63: N/A
A64: =C64&D64&E64&F64 -> Junior DeveloperLEADERSHIPHiring and Org DesignEmployer Brand | B64: 62 | C64: Junior Developer | D64: =weights_editor!A67 -> LEADERSHIP | E64: =weights_editor!B67 -> Hiring and Org Design | F64: =weights_editor!C67 -> Employer Brand | G64: =weights_editor!D67 -> 0 | H64: =weights_editor!E67 -> 0.4 | I64: N/A
A65: =C65&D65&E65&F65 -> Junior DeveloperLEADERSHIPHiring and Org DesignHiring | B65: 63 | C65: Junior Developer | D65: =weights_editor!A68 -> LEADERSHIP | E65: =weights_editor!B68 -> Hiring and Org Design | F65: =weights_editor!C68 -> Hiring | G65: =weights_editor!D68 -> 0 | H65: =weights_editor!E68 -> 0.2 | I65: N/A
A66: =C66&D66&E66&F66 -> Junior DeveloperLEADERSHIPStakeholder Management | B66: 64 | C66: Junior Developer | D66: =weights_editor!A69 -> LEADERSHIP | E66: =weights_editor!B69 -> Stakeholder Management | F66: =weights_editor!C69 | G66: =weights_editor!D69 -> 0.73 | H66: =weights_editor!E69 -> 0.3 | I66: The ability to ensure that teams are protected and expectations are set correctly. Is able to keep tangential teams informed and expectations managed around everyday work updates. Uses judgement about others' reaction when disclosing information and opinions.
A67: =C67&D67&E67&F67 -> Junior DeveloperLEADERSHIPStakeholder ManagementManaging Goals and Expectations | B67: 65 | C67: Junior Developer | D67: =weights_editor!A70 -> LEADERSHIP | E67: =weights_editor!B70 -> Stakeholder Management | F67: =weights_editor!C70 -> Managing Goals and Expectations | G67: =weights_editor!D70 -> 0.5 | H67: =weights_editor!E70 -> 0.4 | I67: You lead on successful projects with external clients, internal stakeholders or partners with a successful outcome, ensuring goals are understood throughout.
A68: =C68&D68&E68&F68 -> Junior DeveloperLEADERSHIPStakeholder ManagementForesight | B68: 66 | C68: Junior Developer | D68: =weights_editor!A71 -> LEADERSHIP | E68: =weights_editor!B71 -> Stakeholder Management | F68: =weights_editor!C71 -> Foresight | G68: =weights_editor!D71 -> 0.8 | H68: =weights_editor!E71 -> 0.3 | I68: You work to inform departments, stakeholders or clients of an issue they face without being asked or expected to do so.
A69: =C69&D69&E69&F69 -> Junior DeveloperLEADERSHIPStakeholder ManagementEngendering Trust | B69: 67 | C69: Junior Developer | D69: =weights_editor!A72 -> LEADERSHIP | E69: =weights_editor!B72 -> Stakeholder Management | F69: =weights_editor!C72 -> Engendering Trust | G69: =weights_editor!D72 -> 1.2 | H69: =weights_editor!E72 -> 0.2 | I69: You bring stakeholders or clients into a process in a way that makes best use of their time and their strengths.
A70: =C70&D70&E70&F70 -> Junior DeveloperLEADERSHIPStakeholder ManagementProtecting the Team | B70: 68 | C70: Junior Developer | D70: =weights_editor!A73 -> LEADERSHIP | E70: =weights_editor!B73 -> Stakeholder Management | F70: =weights_editor!C73 -> Protecting the Team | G70: =weights_editor!D73 -> 0.5 | H70: =weights_editor!E73 -> 0.1 | I70: You manage a client or stakeholder relationship for a project.
A71: =C71&D71&E71&F71 -> Junior DeveloperLEADERSHIPTeam Leadership | B71: 69 | C71: Junior Developer | D71: =weights_editor!A74 -> LEADERSHIP | E71: =weights_editor!B74 -> Team Leadership | F71: =weights_editor!C74 | G71: =weights_editor!D74 -> 0.85 | H71: =weights_editor!E74 -> 0.2 | I71: The ability to maintain quality, efficiency and establish trust in your ability.
A72: =C72&D72&E72&F72 -> Junior DeveloperLEADERSHIPTeam LeadershipPutting the Team first | B72: 70 | C72: Junior Developer | D72: =weights_editor!A75 -> LEADERSHIP | E72: =weights_editor!B75 -> Team Leadership | F72: =weights_editor!C75 -> Putting the Team first | G72: =weights_editor!D75 -> 1 | H72: =weights_editor!E75 -> 0.5 | I72: N/A
A73: =C73&D73&E73&F73 -> Junior DeveloperLEADERSHIPTeam LeadershipDifficult Conversations | B73: 71 | C73: Junior Developer | D73: =weights_editor!A76 -> LEADERSHIP | E73: =weights_editor!B76 -> Team Leadership | F73: =weights_editor!C76 -> Difficult Conversations | G73: =weights_editor!D76 -> 0 | H73: =weights_editor!E76 -> 0.2 | I73: N/A
... A84: =C84&D84&E84&F84 -> Junior DeveloperLEADERSHIPCulture & TogethernessDeveloping personal relationships | B84: 82 | C84: Junior Developer | D84: =weights_editor!A87 -> LEADERSHIP | E84: =weights_editor!B87 -> Culture & Togetherness | F84: =weights_editor!C87 -> Developing personal relationships | G84: =weights_editor!D87 -> 1 | H84: =weights_editor!E87 -> 0.2 | I84: You invest in the relationships you are fostering with your team. You respect the sanctity of pastoral care and 1:1 time. You don't cancel and are never late.
A85: =TRIM(C85&D85&E85&F85) -> Confirmed DeveloperENGINEERING CRAFT | B85: 0 | C85: Confirmed Developer | D85: =weights_editor!A3 -> ENGINEERING CRAFT | E85: =weights_editor!B3 | F85: =weights_editor!C3 | G85: =weights_editor!G3 -> 1.9675 | H85: =weights_editor!H3 -> 0.65
A86: =C86&D86&E86&F86 -> Confirmed DeveloperENGINEERING CRAFTWriting Code | B86: 1 | C86: Confirmed Developer | D86: =weights_editor!A4 -> ENGINEERING CRAFT | E86: =weights_editor!B4 -> Writing Code | F86: =weights_editor!C4 | G86: =weights_editor!G4 -> 1.925 | H86: =weights_editor!H4 -> 0.4 | I86: The ability to contribute high quality code to production environments. Is able to consistently write production-ready code across large, complex projects.
A87: =C87&D87&E87&F87 -> Confirmed DeveloperENGINEERING CRAFTWriting CodeQuality | B87: 2 | C87: Confirmed Developer | D87: =weights_editor!A5 -> ENGINEERING CRAFT | E87: =weights_editor!B5 -> Writing Code | F87: =weights_editor!C5 -> Quality | G87: =weights_editor!G5 -> 2 | H87: =weights_editor!H5 -> 0.45 | I87: You're regularly trusted to lead complex and business-critical coding projects, including guiding others.
A88: =C88&D88&E88&F88 -> Confirmed DeveloperENGINEERING CRAFTWriting CodeDocumentation | B88: 3 | C88: Confirmed Developer | D88: =weights_editor!A6 -> ENGINEERING CRAFT | E88: =weights_editor!B6 -> Writing Code | F88: =weights_editor!C6 -> Documentation | G88: =weights_editor!G6 -> 1.8 | H88: =weights_editor!H6 -> 0.25 | I88: Your code is consistently self-documenting where possible. You've regularly maintained, improved and extended existing documentation unprompted.
A89: =C89&D89&E89&F89 -> Confirmed DeveloperENGINEERING CRAFTWriting CodeLanguage | B89: 4 | C89: Confirmed Developer | D89: =weights_editor!A7 -> ENGINEERING CRAFT | E89: =weights_editor!B7 -> Writing Code | F89: =weights_editor!C7 -> Language | G89: =weights_editor!G7 -> 2.2 | H89: =weights_editor!H7 -> 0.25 | I89: You're committing quality code in any language your team needs OR you're best in class at one language.
A90: =C90&D90&E90&F90 -> Confirmed DeveloperENGINEERING CRAFTWriting CodeMentoring | B90: 5 | C90: Confirmed Developer | D90: =weights_editor!A8 -> ENGINEERING CRAFT | E90: =weights_editor!B8 -> Writing Code | F90: =weights_editor!C8 -> Mentoring | G90: =weights_editor!G8 -> 0.5 | H90: =weights_editor!H8 -> 0.05 | I90: You have mentored several junior engineers around code quality.
A91: =C91&D91&E91&F91 -> Confirmed DeveloperENGINEERING CRAFTTesting | B91: 6 | C91: Confirmed Developer | D91: =weights_editor!A9 -> ENGINEERING CRAFT | E91: =weights_editor!B9 -> Testing | F91: =weights_editor!C9 | G91: =weights_editor!G9 -> 2.45 | H91: =weights_editor!H9 -> 0.15 | I91: The ability to understand and implement great testing practices. Understands the importance of a testing strategy, with growing levels of autonomy.
A92: =C92&D92&E92&F92 -> Confirmed DeveloperENGINEERING CRAFTTestingTesting your code | B92: 7 | C92: Confirmed Developer | D92: =weights_editor!A10 -> ENGINEERING CRAFT | E92: =weights_editor!B10 -> Testing | F92: =weights_editor!C10 -> Testing your code | G92: =weights_editor!G10 -> 2.8 | H92: =weights_editor!H10 -> 0.6 | I92: You usually write detailed unit and functional tests covering edge cases as well as happy paths.
A93: =C93&D93&E93&F93 -> Confirmed DeveloperENGINEERING CRAFTTestingImproving coverage | B93: 8 | C93: Confirmed Developer | D93: =weights_editor!A11 -> ENGINEERING CRAFT | E93: =weights_editor!B11 -> Testing | F93: =weights_editor!C11 -> Improving coverage | G93: =weights_editor!G11 -> 2 | H93: =weights_editor!H11 -> 0.25 | I93: You've improved test coverage in adjacent areas of code to your own without being asked.
A94: =C94&D94&E94&F94 -> Confirmed DeveloperENGINEERING CRAFTTestingTaking responsibility | B94: 9 | C94: Confirmed Developer | D94: =weights_editor!A12 -> ENGINEERING CRAFT | E94: =weights_editor!B12 -> Testing | F94: =weights_editor!C12 -> Taking responsibility | G94: =weights_editor!G12 -> 1.8 | H94: =weights_editor!H12 -> 0.15 | I94: You've ensured that code committed by your immediate team is well tested and passing
A95: =C95&D95&E95&F95 -> Confirmed DeveloperENGINEERING CRAFTTestingLeading testing strategy | B95: 10 | C95: Confirmed Developer | D95: =weights_editor!A13 -> ENGINEERING CRAFT | E95: =weights_editor!B13 -> Testing | F95: =weights_editor!C13 -> Leading testing strategy | G95: =weights_editor!G13 -> 0 | H95: =weights_editor!H13 -> 0 | I95: N/A
A96: =C96&D96&E96&F96 -> Confirmed DeveloperENGINEERING CRAFTTestingAdvocating for testing | B96: 11 | C96: Confirmed Developer | D96: =weights_editor!A14 -> ENGINEERING CRAFT | E96: =weights_editor!B14 -> Testing | F96: =weights_editor!C14 -> Advocating for testing | G96: =weights_editor!G14 -> 0 | H96: =weights_editor!H14 -> 0 | I96: N/A
A97: =C97&D97&E97&F97 -> Confirmed DeveloperENGINEERING CRAFTTechnical Understanding & Prioritisation | B97: 12 | C97: Confirmed Developer | D97: =weights_editor!A15 -> ENGINEERING CRAFT | E97: =weights_editor!B15 -> Technical Understanding & Prioritisation | F97: =weights_editor!C15 | G97: =weights_editor!G15 -> 2.07 | H97: =weights_editor!H15 -> 0.15 | I97: The ability to develop technical understanding and use this to prioritise tasks appropriately. Is able to display a clear technical confidence and understanding, prioritises tasks and acts accordingly.
... A121: =C121&D121&E121&F121 -> Confirmed DeveloperENGINEERING CRAFTDebugging & MonitoringMentoring | B121: 36 | C121: Confirmed Developer | D121: =weights_editor!A39 -> ENGINEERING CRAFT | E121: =weights_editor!B39 -> Debugging & Monitoring | F121: =weights_editor!C39 -> Mentoring | G121: =weights_editor!G39 -> 0 | H121: =weights_editor!H39 -> 0 | I121: N/A
A122: =C122&D122&E122&F122 -> Confirmed DeveloperSOFT SKILLS | B122: 37 | C122: Confirmed Developer | D122: =weights_editor!A41 -> SOFT SKILLS | E122: =weights_editor!B41 | F122: =weights_editor!C41 | G122: =weights_editor!G41 -> 1.7285 | H122: =weights_editor!H41 -> 0.3
A123: =C123&D123&E123&F123 -> Confirmed DeveloperSOFT SKILLSEmpathy & Humility | B123: 38 | C123: Confirmed Developer | D123: =weights_editor!A42 -> SOFT SKILLS | E123: =weights_editor!B42 -> Empathy & Humility | F123: =weights_editor!C42 | G123: =weights_editor!G42 -> 1.53 | H123: =weights_editor!H42 -> 0.4 | I123: The ability to share someone else's feelings or experiences by imagining what it would be like to be in that person's situation. Constantly pushes for a better understanding of the needs and perspectives of those outside their own viewpoint.
A124: =C124&D124&E124&F124 -> Confirmed DeveloperSOFT SKILLSEmpathy & HumilityCredit and blame | B124: 39 | C124: Confirmed Developer | D124: =weights_editor!A43 -> SOFT SKILLS | E124: =weights_editor!B43 -> Empathy & Humility | F124: =weights_editor!C43 -> Credit and blame | G124: =weights_editor!G43 -> 1.8 | H124: =weights_editor!H43 -> 0.3 | I124: You actively look to ensure praise is shared fairly when given to you. If someone else is blamed for your mistake, you own up.
A125: =C125&D125&E125&F125 -> Confirmed DeveloperSOFT SKILLSEmpathy & HumilityUnderstanding others | B125: 40 | C125: Confirmed Developer | D125: =weights_editor!A44 -> SOFT SKILLS | E125: =weights_editor!B44 -> Empathy & Humility | F125: =weights_editor!C44 -> Understanding others | G125: =weights_editor!G44 -> 2.1 | H125: =weights_editor!H44 -> 0.3 | I125: You regularly and actively ask others for their opinions with the goal of better understanding where they're coming from.
A126: =C126&D126&E126&F126 -> Confirmed DeveloperSOFT SKILLSEmpathy & HumilityMediation and facilitation | B126: 41 | C126: Confirmed Developer | D126: =weights_editor!A45 -> SOFT SKILLS | E126: =weights_editor!B45 -> Empathy & Humility | F126: =weights_editor!C45 -> Mediation and facilitation | G126: =weights_editor!G45 -> 1.3 | H126: =weights_editor!H45 -> 0.2 | I126: You have de-escalated disagreements amongst your peers, looking for common ground.
A127: =C127&D127&E127&F127 -> Confirmed DeveloperSOFT SKILLSEmpathy & HumilityMentoring | B127: 42 | C127: Confirmed Developer | D127: =weights_editor!A46 -> SOFT SKILLS | E127: =weights_editor!B46 -> Empathy & Humility | F127: =weights_editor!C46 -> Mentoring | G127: =weights_editor!G46 -> 0.5 | H127: =weights_editor!H46 -> 0.2 | I127: You've proactively developed at least one informal mentoring relationship through your ability to understand a peer or subordinate.
A128: =C128&D128&E128&F128 -> Confirmed DeveloperSOFT SKILLSCommunication | B128: 43 | C128: Confirmed Developer | D128: =weights_editor!A47 -> SOFT SKILLS | E128: =weights_editor!B47 -> Communication | F128: =weights_editor!C47 | G128: =weights_editor!G47 -> 1.6 | H128: =weights_editor!H47 -> 0.25 | I128: The ability to communicate well with those around you with sensitivity to timeliness, medium, brevity and tone. Communicates with wider team, feeds back on communication of others.
A129: =C129&D129&E129&F129 -> Confirmed DeveloperSOFT SKILLSCommunicationKeeping people informed | B129: 44 | C129: Confirmed Developer | D129: =weights_editor!A48 -> SOFT SKILLS | E129: =weights_editor!B48 -> Communication | F129: =weights_editor!C48 -> Keeping people informed | G129: =weights_editor!G48 -> 1.6 | H129: =weights_editor!H48 -> 0.5 | I129: You communicate work updates from your peers across your wider team, and respond to feedback in a timely manner.
A130: =C130&D130&E130&F130 -> Confirmed DeveloperSOFT SKILLSCommunicationLooking for feedback | B130: 45 | C130: Confirmed Developer | D130: =weights_editor!A49 -> SOFT SKILLS | E130: =weights_editor!B49 -> Communication | F130: =weights_editor!C49 -> Looking for feedback | G130: =weights_editor!G49 -> 2.4 | H130: =weights_editor!H49 -> 0.25 | I130: You consistently ask for critique on your thinking from a wider group, and inform the group which elements you're incorporating into your work.
A131: =C131&D131&E131&F131 -> Confirmed DeveloperSOFT SKILLSCommunicationDelivering bad news | B131: 46 | C131: Confirmed Developer | D131: =weights_editor!A50 -> SOFT SKILLS | E131: =weights_editor!B50 -> Communication | F131: =weights_editor!C50 -> Delivering bad news | G131: =weights_editor!G50 -> 1 | H131: =weights_editor!H50 -> 0.15 | I131: You recognise when you need help from outside your immediate peers and asked for it effectively.
A132: =C132&D132&E132&F132 -> Confirmed DeveloperSOFT SKILLSCommunicationMentoring communicators | B132: 47 | C132: Confirmed Developer | D132: =weights_editor!A51 -> SOFT SKILLS | E132: =weights_editor!B51 -> Communication | F132: =weights_editor!C51 -> Mentoring communicators | G132: =weights_editor!G51 -> 0.5 | H132: =weights_editor!H51 -> 0.1 | I132: You are able to unpick the communication of others around you and offer advice and feedback.
A133: =C133&D133&E133&F133 -> Confirmed DeveloperSOFT SKILLSInitiative | B133: 48 | C133: Confirmed Developer | D133: =weights_editor!A52 -> SOFT SKILLS | E133: =weights_editor!B52 -> Initiative | F133: =weights_editor!C52 | G133: =weights_editor!G52 -> 2.15 | H133: =weights_editor!H52 -> 0.2 | I133: The ability to use your judgment to make decisions and do things without needing to be told what to do. You show a good intuition for code interface design.
A134: =C134&D134&E134&F134 -> Confirmed DeveloperSOFT SKILLSInitiativeCan-do attitude | B134: 49 | C134: Confirmed Developer | D134: =weights_editor!A53 -> SOFT SKILLS | E134: =weights_editor!B53 -> Initiative | F134: =weights_editor!C53 -> Can-do attitude | G134: =weights_editor!G53 -> 2.4 | H134: =weights_editor!H53 -> 0.55 | I134: You see opportunity in every piece of work, however outwardly mundane or solved.
... A141: =C141&D141&E141&F141 -> Confirmed DeveloperSOFT SKILLSObjectivity & AdaptabilityTime management | B141: 56 | C141: Confirmed Developer | D141: =weights_editor!A60 -> SOFT SKILLS | E141: =weights_editor!B60 -> Objectivity & Adaptability | F141: =weights_editor!C60 -> Time management | G141: =weights_editor!G60 -> 1.9 | H141: =weights_editor!H60 -> 0.05 | I141: You actively flag when you think something can be achieved more quickly, even if it was your plan initially and it will involve admitting fault.
A142: =C142&D142&E142&F142 -> Confirmed DeveloperSOFT SKILLSBusiness Acumen | B142: 57 | C142: Confirmed Developer | D142: =weights_editor!A61 -> SOFT SKILLS | E142: =weights_editor!B61 -> Business Acumen | F142: =weights_editor!C61 | G142: =weights_editor!G61 -> 1.4 | H142: =weights_editor!H61 -> 0.05
A143: =C143&D143&E143&F143 -> Confirmed DeveloperSOFT SKILLSBusiness AcumenUnderstanding level | B143: 58 | C143: Confirmed Developer | D143: =weights_editor!A62 -> SOFT SKILLS | E143: =weights_editor!B62 -> Business Acumen | F143: =weights_editor!C62 -> Understanding level | G143: =weights_editor!G62 -> 1.4 | H143: =weights_editor!H62 -> 1 | I143: Has a basic understanding of their team's domain, and how it contributes to overall business strategy.
A144: =C144&D144&E144&F144 -> Confirmed DeveloperLEADERSHIP | B144: 59 | C144: Confirmed Developer | D144: =weights_editor!A64 -> LEADERSHIP | E144: =weights_editor!B64 | F144: =weights_editor!C64 | G144: =weights_editor!G64 -> 0.933 | H144: =weights_editor!H64 -> 0.05
A145: =C145&D145&E145&F145 -> Confirmed DeveloperLEADERSHIPHiring and Org Design | B145: 60 | C145: Confirmed Developer | D145: =weights_editor!A65 -> LEADERSHIP | E145: =weights_editor!B65 -> Hiring and Org Design | F145: =weights_editor!C65 | G145: =weights_editor!G65 -> 0.2 | H145: =weights_editor!H65 -> 0.2 | I145: The ability to understand the needs of the business and ensure that your team can meet them. A competent interviewer. Able to follow a structured hiring process, and make a decision.
A146: =C146&D146&E146&F146 -> Confirmed DeveloperLEADERSHIPHiring and Org DesignDeploying Teams | B146: 61 | C146: Confirmed Developer | D146: =weights_editor!A66 -> LEADERSHIP | E146: =weights_editor!B66 -> Hiring and Org Design | F146: =weights_editor!C66 -> Deploying Teams | G146: =weights_editor!G66 -> 0 | H146: =weights_editor!H66 -> 0.4 | I146: You've carved out an additional role for yourself or peers to fulfil a need that a team has.
A147: =C147&D147&E147&F147 -> Confirmed DeveloperLEADERSHIPHiring and Org DesignEmployer Brand | B147: 62 | C147: Confirmed Developer | D147: =weights_editor!A67 -> LEADERSHIP | E147: =weights_editor!B67 -> Hiring and Org Design | F147: =weights_editor!C67 -> Employer Brand | G147: =weights_editor!G67 -> 0.5 | H147: =weights_editor!H67 -> 0.4 | I147: You've helped to establish the company as a good employer through promotion on stage or online. You've inputted into the company's careers pages.
A148: =C148&D148&E148&F148 -> Confirmed DeveloperLEADERSHIPHiring and Org DesignHiring | B148: 63 | C148: Confirmed Developer | D148: =weights_editor!A68 -> LEADERSHIP | E148: =weights_editor!B68 -> Hiring and Org Design | F148: =weights_editor!C68 -> Hiring | G148: =weights_editor!G68 -> 0 | H148: =weights_editor!H68 -> 0.2 | I148: You are regularly part of hiring panels, and have been hiring manager for at least one hire that passed probation.
A149: =C149&D149&E149&F149 -> Confirmed DeveloperLEADERSHIPStakeholder Management | B149: 64 | C149: Confirmed Developer | D149: =weights_editor!A69 -> LEADERSHIP | E149: =weights_editor!B69 -> Stakeholder Management | F149: =weights_editor!C69 | G149: =weights_editor!G69 -> 1.35 | H149: =weights_editor!H69 -> 0.3 | I149: The ability to ensure that teams are protected and expectations are set correctly. Known for being efficient and reliable, and doing what they say they will do. Proactively managed expectations even when it results in frustration or personal reputation risk.
A150: =C150&D150&E150&F150 -> Confirmed DeveloperLEADERSHIPStakeholder ManagementManaging Goals and Expectations | B150: 65 | C150: Confirmed Developer | D150: =weights_editor!A70 -> LEADERSHIP | E150: =weights_editor!B70 -> Stakeholder Management | F150: =weights_editor!C70 -> Managing Goals and Expectations | G150: =weights_editor!G70 -> 1.1 | H150: =weights_editor!H70 -> 0.4 | I150: You lead multiple smaller projects with external clients or internal stakeholders, with a successful outcome.
A151: =C151&D151&E151&F151 -> Confirmed DeveloperLEADERSHIPStakeholder ManagementForesight | B151: 66 | C151: Confirmed Developer | D151: =weights_editor!A71 -> LEADERSHIP | E151: =weights_editor!B71 -> Stakeholder Management | F151: =weights_editor!C71 -> Foresight | G151: =weights_editor!G71 -> 1.4 | H151: =weights_editor!H71 -> 0.3 | I151: You anticipate issues or requirements on projects in advance and work to raise those with key people outside your team. This has resulted in noticeable efficiency gains.
A152: =C152&D152&E152&F152 -> Confirmed DeveloperLEADERSHIPStakeholder ManagementEngendering Trust | B152: 67 | C152: Confirmed Developer | D152: =weights_editor!A72 -> LEADERSHIP | E152: =weights_editor!B72 -> Stakeholder Management | F152: =weights_editor!C72 -> Engendering Trust | G152: =weights_editor!G72 -> 1.8 | H152: =weights_editor!H72 -> 0.2 | I152: You run several small to medium sized projects in a leadership capacity, working closely with clients and stakeholders with positive reviews.
A153: =C153&D153&E153&F153 -> Confirmed DeveloperLEADERSHIPStakeholder ManagementProtecting the Team | B153: 68 | C153: Confirmed Developer | D153: =weights_editor!A73 -> LEADERSHIP | E153: =weights_editor!B73 -> Stakeholder Management | F153: =weights_editor!C73 -> Protecting the Team | G153: =weights_editor!G73 -> 1.3 | H153: =weights_editor!H73 -> 0.1 | I153: You create space for others in your team to do their best work by managing client or stakeholder relationships.
A154: =C154&D154&E154&F154 -> Confirmed DeveloperLEADERSHIPTeam Leadership | B154: 69 | C154: Confirmed Developer | D154: =weights_editor!A74 -> LEADERSHIP | E154: =weights_editor!B74 -> Team Leadership | F154: =weights_editor!C74 | G154: =weights_editor!G74 -> 1.22 | H154: =weights_editor!H74 -> 0.2 | I154: The ability to maintain quality, efficiency and establish trust in your ability.
A155: =C155&D155&E155&F155 -> Confirmed DeveloperLEADERSHIPTeam LeadershipPutting the Team first | B155: 70 | C155: Confirmed Developer | D155: =weights_editor!A75 -> LEADERSHIP | E155: =weights_editor!B75 -> Team Leadership | F155: =weights_editor!C75 -> Putting the Team first | G155: =weights_editor!G75 -> 1.5 | H155: =weights_editor!H75 -> 0.5 | I155: N/A
A156: =C156&D156&E156&F156 -> Confirmed DeveloperLEADERSHIPTeam LeadershipDifficult Conversations | B156: 71 | C156: Confirmed Developer | D156: =weights_editor!A76 -> LEADERSHIP | E156: =weights_editor!B76 -> Team Leadership | F156: =weights_editor!C76 -> Difficult Conversations | G156: =weights_editor!G76 -> 0.2 | H156: =weights_editor!H76 -> 0.2 | I156: N/A
... A167: =C167&D167&E167&F167 -> Confirmed DeveloperLEADERSHIPCulture & TogethernessDeveloping personal relationships | B167: 82 | C167: Confirmed Developer | D167: =weights_editor!A87 -> LEADERSHIP | E167: =weights_editor!B87 -> Culture & Togetherness | F167: =weights_editor!C87 -> Developing personal relationships | G167: =weights_editor!G87 -> 1.2 | H167: =weights_editor!H87 -> 0.2 | I167: You invest in the relationships you are fostering with your team. You respect the sanctity of pastoral care and 1:1 time. You don't cancel and are never late.
A168: =TRIM(C168&D168&E168&F168) -> Senior DeveloperENGINEERING CRAFT | B168: 0 | C168: Senior Developer | D168: =weights_editor!A3 -> ENGINEERING CRAFT | E168: =weights_editor!B3 | F168: =weights_editor!C3 | G168: =weights_editor!J3 -> 2.5345 | H168: =weights_editor!K3 -> 0.6
A169: =C169&D169&E169&F169 -> Senior DeveloperENGINEERING CRAFTWriting Code | B169: 1 | C169: Senior Developer | D169: =weights_editor!A4 -> ENGINEERING CRAFT | E169: =weights_editor!B4 -> Writing Code | F169: =weights_editor!C4 | G169: =weights_editor!J4 -> 2.51 | H169: =weights_editor!K4 -> 0.35 | I169: The ability to contribute high quality code to production environments. Is able to consistently write production-ready code across large, complex projects.
A170: =C170&D170&E170&F170 -> Senior DeveloperENGINEERING CRAFTWriting CodeQuality | B170: 2 | C170: Senior Developer | D170: =weights_editor!A5 -> ENGINEERING CRAFT | E170: =weights_editor!B5 -> Writing Code | F170: =weights_editor!C5 -> Quality | G170: =weights_editor!J5 -> 2.6 | H170: =weights_editor!K5 -> 0.4 | I170: You're regularly trusted to lead complex and business-critical coding projects, including guiding others.
A171: =C171&D171&E171&F171 -> Senior DeveloperENGINEERING CRAFTWriting CodeDocumentation | B171: 3 | C171: Senior Developer | D171: =weights_editor!A6 -> ENGINEERING CRAFT | E171: =weights_editor!B6 -> Writing Code | F171: =weights_editor!C6 -> Documentation | G171: =weights_editor!J6 -> 2.4 | H171: =weights_editor!K6 -> 0.2 | I171: Your code is consistently self-documenting where possible. You've regularly maintained, improved and extended existing documentation unprompted.
A172: =C172&D172&E172&F172 -> Senior DeveloperENGINEERING CRAFTWriting CodeLanguage | B172: 4 | C172: Senior Developer | D172: =weights_editor!A7 -> ENGINEERING CRAFT | E172: =weights_editor!B7 -> Writing Code | F172: =weights_editor!C7 -> Language | G172: =weights_editor!J7 -> 2.8 | H172: =weights_editor!K7 -> 0.3 | I172: You're committing quality code in any language your team needs OR you're best in class at one language.
A173: =C173&D173&E173&F173 -> Senior DeveloperENGINEERING CRAFTWriting CodeMentoring | B173: 5 | C173: Senior Developer | D173: =weights_editor!A8 -> ENGINEERING CRAFT | E173: =weights_editor!B8 -> Writing Code | F173: =weights_editor!C8 -> Mentoring | G173: =weights_editor!J8 -> 1.5 | H173: =weights_editor!K8 -> 0.1 | I173: You have mentored several junior engineers around code quality.
A174: =C174&D174&E174&F174 -> Senior DeveloperENGINEERING CRAFTTesting | B174: 6 | C174: Senior Developer | D174: =weights_editor!A9 -> ENGINEERING CRAFT | E174: =weights_editor!B9 -> Testing | F174: =weights_editor!C9 | G174: =weights_editor!J9 -> 2.92 | H174: =weights_editor!K9 -> 0.15 | I174: The ability to understand and implement great testing practices. Independently testing, advising the rest of the team on quality of tests.
A175: =C175&D175&E175&F175 -> Senior DeveloperENGINEERING CRAFTTestingTesting your code | B175: 7 | C175: Senior Developer | D175: =weights_editor!A10 -> ENGINEERING CRAFT | E175: =weights_editor!B10 -> Testing | F175: =weights_editor!C10 -> Testing your code | G175: =weights_editor!J10 -> 3.2 | H175: =weights_editor!K10 -> 0.5 | I175: You always write full tests for your code unassisted, covering all edge cases even with complex functionality.
A176: =C176&D176&E176&F176 -> Senior DeveloperENGINEERING CRAFTTestingImproving coverage | B176: 8 | C176: Senior Developer | D176: =weights_editor!A11 -> ENGINEERING CRAFT | E176: =weights_editor!B11 -> Testing | F176: =weights_editor!C11 -> Improving coverage | G176: =weights_editor!J11 -> 2.8 | H176: =weights_editor!K11 -> 0.3 | I176: You've worked to improve the quality of your own and your team's test coverage.
A177: =C177&D177&E177&F177 -> Senior DeveloperENGINEERING CRAFTTestingTaking responsibility | B177: 9 | C177: Senior Developer | D177: =weights_editor!A12 -> ENGINEERING CRAFT | E177: =weights_editor!B12 -> Testing | F177: =weights_editor!C12 -> Taking responsibility | G177: =weights_editor!J12 -> 2.4 | H177: =weights_editor!K12 -> 0.2 | I177: You consistently look for and can recall quality metrics to demonstrate your test coverage, and monitor in behalf of your team.
A178: =C178&D178&E178&F178 -> Senior DeveloperENGINEERING CRAFTTestingLeading testing strategy | B178: 10 | C178: Senior Developer | D178: =weights_editor!A13 -> ENGINEERING CRAFT | E178: =weights_editor!B13 -> Testing | F178: =weights_editor!C13 -> Leading testing strategy | G178: =weights_editor!J13 -> 1 | H178: =weights_editor!K13 -> 0 | I178: N/A
...

Sheet Base career path evaluation gri
A1: SKILLS | AG1: April 2022 | AI1: CONFIRMED | AK1: July 2022 | AM1: SENIOR | AO1: LEGEND
C2: Junior Software Engineer (associate) | I2: Confirmed Software Engineer | O2: Senior Software Engineer | U2: Lead Software Engineer | AA2: Principal Software Engineer | AG2: Level | AH2: Success | AI2: Ideas for improvements | AK2: Level | AL2: Success | AM2: Ideas for improvements
A3: SOFT SKILLS | AO3: LIVE CURSOR
A4: Empathy & Humility | AG4: 🆙 3 / 2 | AH4: This is great! Focus elsewhere. | AO4: 🖐 | AP4: Tells current position on this skills.
A5: The ability to share someone else's feelings or experiences by imagining what it would be like to be in that person's situation | C5: Constantly pushes for a better understanding of the needs and perspectives of those outside their own viewpoint. | I5: Constantly pushes for a better understanding of the needs and perspectives of those outside their own viewpoint. | O5: A great person to have in any room. Trusted by peers and their team. Can take any problem team and help them drive in the same direction. | U5: Often found advocating for and representing others in conversations they cannot be in. Helps leaders to understand their teams, users and clients. | AA5: Often found advocating for and representing others in conversations they cannot be in. Helps leaders to understand their teams, users and clients. | AH5: - item 1 - item 2 | AI5: - Q1 : TBD - Q2 : TBD
C6: • Credit and blame: You actively look to ensure praise is shared fairly when given to you. If someone else is blamed for your mistake, you own up. • Understanding others: You regularly and actively ask others for their opinions with the goal of better understanding where they're coming from. • Mediation and facilitation: You have de-escalated disagreements amongst your peers, looking for common ground. • Mentoring: You've proactively developed at least one informal mentoring relationship through your ability to understand a peer or subordinate. | I6: • Credit and blame: You actively look to ensure praise is shared fairly when given to you. If someone else is blamed for your mistake, you own up. • Understanding others: You regularly and actively ask others for their opinions with the goal of better understanding where they're coming from. • Mediation and facilitation: You have de-escalated disagreements amongst your peers, looking for common ground. • Mentoring: You've proactively developed at least one informal mentoring relationship through your ability to understand a peer or subordinate. | O6: • Credit and blame: You're an ally to your peers and wider team, protecting them from undue blame and pushing praise onto them. You regularly look for opportunities to give praise publicly. • Understanding others: You are able to recognise bias in others and help them to see their peers, customers or stakeholders through fresh eyes. • Mediation and facilitation: You help teams within your organisation get closer to each other and understand each other's viewpoints. • Mentoring: You've proactively developed multiple informal or formal mentoring relationship through your ability to understand a peer or subordinate. | U6: • Credit and blame: You use your position of power to redirect credit fairly, and absorb blame that isn't constructive to your team. • Understanding others: You're called for when any team wants to understand a group of people better. You can point to ways in which you've actively looked to dramatically improve the empathy of your organisation. • Mediation and facilitation: You're called on to facilitate groups of people, often outside your peers, due to your calm and thoughtful demeanour. You make even combative people feel calm through finding common ground. • Mentoring: You have several formal mentoring relationships with senior staff both within and outside your immediate team. | AA6: • Credit and blame: You use your position of power to redirect credit fairly, and absorb blame that isn't constructive to your team. • Understanding others: You're called for when any team wants to understand a group of people better. You can point to ways in which you've actively looked to dramatically improve the empathy of your organisation. • Mediation and facilitation: You're called on to facilitate groups of people, often outside your peers, due to your calm and thoughtful demeanour. You make even combative people feel calm through finding common ground. • Mentoring: You have several formal mentoring relationships with senior staff both within and outside your immediate team.
A7: Communication | AG7: ⚠️ 1 / 2 | AH7: Need to work on this to evolve
A8: The ability to communicate well with those around you with sensitivity to timeliness, medium, brevity and tone | C8: Communicates with wider team, feeds back on communication of others. | I8: Communicates with wider team, feeds back on communication of others. | O8: Communicates with organisation, helps others in team to communicate | U8: Communicates with organisation, helps others in team to communicate | AA8: Communicates with the wider business, including change affecting the work of others, helps teams around them to communicate better. | AH8: - item 1 - item 2 | AI8: - Q1 : TBD - Q2 : TBD
C9: • Keeping people informed: You communicate work updates from your peers across your wider team, and respond to feedback in a timely manner. • Looking for feedback: You consistently ask for critique on your thinking from a wider group, and inform the group which elements you're incorporating into your work. • Delivering bad news: You recognise when you need help from outside your immediate peers and asked for it effectively. • Mentoring communicators: You are able to unpick the communication of others around you and offer advice and feedback. | I9: • Keeping people informed: You communicate work updates from your peers across your wider team, and respond to feedback in a timely manner. • Looking for feedback: You consistently ask for critique on your thinking from a wider group, and inform the group which elements you're incorporating into your work. • Delivering bad news: You recognise when you need help from outside your immediate peers and asked for it effectively. • Mentoring communicators: You are able to unpick the communication of others around you and offer advice and feedback. | O9: • Keeping people informed: You communicate on behalf of your team to the broader organisation on important or divisive projects, handling any questions in a timely manner. • Looking for feedback: You proactively ask for feedback from important stakeholders in your organisation early in your work. • Delivering bad news: You communicate changes of plan or slip in timelines to a broad group within your organisation and manage expectations effectively until resolution. • Mentoring communicators: You set up processes around more effective communication for your immediate team, and manage its implementation. You proactively offer good feedback to peers on their communication methods. | U9: • Keeping people informed: You communicate on behalf of your team to the broader organisation on important or divisive projects, handling any questions in a timely manner. • Looking for feedback: You proactively ask for feedback from important stakeholders in your organisation early in your work. • Delivering bad news: You communicate changes of plan or slip in timelines to a broad group within your organisation and manage expectations effectively until resolution. • Mentoring communicators: You set up processes around more effective communication for your immediate team, and manage its implementation. You proactively offer good feedback to peers on their communication methods. | AA9: • Keeping people informed: You design the process of communication to communicate with the business around strategically important projects using appropriate mediums. • Looking for feedback: You communicate changes in plans, organisational structure or work situation which directly affects one or more people, and manage any fall out from that change ensuring all parties stay informed and content. • Delivering bad news: You communicate bad news to a group of reports or peers, ensuring that a strategy is in place to manage expectations and morale during the change. Your approach involves thoughtfully designed communication to the top levels of the organisation • Mentoring communicators: You regularly mentor others on communication technique, unpick poor communication in your wider organisation and add process where needed. You're comfortable feeding back on the communication of your seniors.
A10: Initiative | AG10: 🆙 3 / 2 | AH10: This is great! KEEP UP! | AO10: HISTORY
A11: The ability to use your judgment to make decisions and do things without needing to be told what to do | C11: Doesn't wait to be asked. Open minded about their own skillset. | I11: Relentlessly positive in pursuing new ways to solve a problem. | O11: Refuses to believe that anything is unachievable. Infectious desire to activate and progress. Drives others to create their best work. Like a rocket: just light the fuse. | U11: Refuses to believe that anything is unachievable. Infectious desire to activate and progress. Drives others to create their best work. Like a rocket: just light the fuse. | AA11: Asks a lot, expects the impossible. Drives others to create their best work. Sees opportunities in everything. | AH11: - item 1 - item 2 | AI11: - Q1 : TBD - Q2 : TBD
C12: • Can-do attitude: You repeatedly demonstrate a positive attitude when given new projects. • Pro-activity in seeking help: If you're stuck on something, you seek help quickly from the correct party. • Follow through: You've taken on a small piece of work with ill-defined or unknown requirements and helped to push through to a successful outcome. | I12: • Can-do attitude: You see opportunity in every piece of work, however outwardly mundane or solved. • Pro-activity in seeking help: When your team is stuck on something, you are quick to suggest that you all adjust focus, reframe a problem or talk to someone new. • Follow through: You lead medium to large projects with unknown requirements and helped drive to a successful outcome. | O12: • Can-do attitude: You're constantly creating new opportunities for yourself and those around you. Your team is celebrated for innovation as a result of your contributions. • Pro-activity in seeking help: You recognise a lack of expertise in yourself and your organisation, and pro-actively found that expertise in areas not given to you. This leads to a successful outcome on more than one occasion. • Follow through: You adapt your skillset and knowledge to lead large or complex projects to a successful outcome. | U12: • Can-do attitude: You're constantly creating new opportunities for yourself and those around you. Your team is celebrated for innovation as a result of your contributions. • Pro-activity in seeking help: You recognise a lack of expertise in yourself and your organisation, and pro-actively found that expertise in areas not given to you. This leads to a successful outcome on more than one occasion. • Follow through: You adapt your skillset and knowledge to lead large or complex projects to a successful outcome. | AA12: • Can-do attitude: YYou take ill-defined requirements and lead a large group within your organisation to make progress on them. • Pro-activity in seeking help: You build relationships with people across your organisation without being asked, expressly for the purpose of boosting your ability to achieve great results. • Follow through: You're deeply involved in projects which require your ability to move through uncertainty. You adapt your skillset appropriately for those projects, morphing into what the projects need you to be.
A13: Objectivity & Adaptability | AG13: ✅ 2 / 2 | AO13: 🆙 2 / 1 | AP13: Above expectations.
A14: The ability to deal with problems based on conditions that really exist, rather than following fixed theories, ideas, or rules, and to adapt to suit different conditions | C14: Able to be objective in evaluating their own work and comfortable and accepting of new contexts and roles. | I14: Is able to change their mind over strongly-held beliefs and pursue a new path with no loss of velocity. | O14: Can take problems outside their skillset and quickly adapt to solve them. Helps other peers to do the same. | U14: Leads others in looking for ways to better serve business or customer needs, even outside their own discipline. Willing to lead mundane but important tasks and help whole teams to move on their goals through simplifying and breaking down problems. | AA14: ← | AH14: - item 1 - item 2 | AI14: - Q1 : TBD - Q2 : TBD
C15: • Efficient decision-making: You regularly make decisions regarding the direction of your own work in a timely manner. • Self improvement: You can name three activities which give you energy, and three which drain you. • Objectivity: You allow your plan to be changed by new information. • Time management: You look to reduce or change the scope of your work to meet a timeline or criteria not set by you. | I15: • Efficient decision-making: You help your immediate peers to make decisions based on what projects need, not what they feel most comfortable doing. • Self improvement: You use your development areas to build improvement goals for yourself and see improvements over time. • Objectivity: You look for new information, assuming that you don't know everything. You can point to examples when you had a strong opinion changed for the better. • Time management: You actively flag when you think something can be achieved more quickly, even if it was your plan initially and it will involve admitting fault. | O15: • Efficient decision-making: You help your team to make decisions in a more timely manner, breaking down assumptions about the shape of the work and encouraging people to value done over perfect. • Self improvement: You can point to several areas of improvement resulting from your focus on improving development areas over time. • Objectivity: You are positive in the face of dramatic changes of plans. Curveballs are dealt with sensibly without frustration. • Time management: You're in control of your calendar. You take no issue with not being involved in a project or meeting if it means saving you time. | U15: • Efficient decision-making: You're part of decision-making teams on several major company-wide initiatives, employing appropriate processes and techniques. • Self improvement: You build processes for yourself and others around you, diagnosing development areas and figuring out better ways of working and collaborating. You champion self improvement in your organisation. • Objectivity: You know which hills to die on. You recognise the importance of believability and pragmatism as a tool for moving product and business forwards, and when to stand your ground. • Time management: You are constantly checking your own plans and the plans of your team for opportunities to change or reduce effort. You exclusively pick up the most important, not the most interesting tasks. | AA15: ←
A16: Business Acumen | AG16: ✅ 2 / 2 | AO16: ✅ 1 / 1 | AP16: Meet expectations.
C17: Has a basic understanding of their team's domain and related marketplace. | I17: Has a basic understanding of their team's domain, and how it contributes to overall business strategy. | O17: Has a thorough understanding of their team's domain, and how it contributes to overall business strategy. Has a basic understanding of adjacent teams' business domains. | U17: Has a thorough understanding of their team's domain, and how it contributes to overall business strategy. Has a basic understanding of adjacent teams' business domains. | AA17: Has a thourough understanding of their team's domain, strategy, and how it maps to overall market trends. Has a thorough understanding of adjacent teams' strategies and how they map to their team and interaction points. | AH17: - item 1 - item 2 | AI17: - Q1 : TBD - Q2 : TBD
AO19: ⚠️ 0 / 1 | AP19: Below expectations.
A20: ENGINEERING CRAFT
A21: Writing Code | AG21: ✅ 5 / 3
A22: The ability to contribute high quality code to production environments | C22: Is able to consistently write testable, readable code across larger more complex projects | I22: Is able to consistently write production-ready code across large, complex projects | O22: Is able to consistently write production-ready code across large, complex projects | U22: Is a go-to within the team and the wider organization across multiple codebases and languages. | AA22: Is an exceptional engineer beyond the organization, contributing to pushing the craft forwards | AH22: - item 1 - item 2 | AI22: - Q1 : TBD - Q2 : TBD
C23: • Quality: Your code has always followed correct convention, requiring only minor improvements. You've made trade-offs knowingly. • Documentation: You've regularly documented your code and looked to improve documentation elsewhere. • Language: You're committing quality code in at least one language and have a working understanding of other languages your team needs | I23: • Quality: You're regularly trusted to lead complex and business-critical coding projects, including guiding others. • Documentation: Your code is consistently self-documenting where possible. You've regularly maintained, improved and extended existing documentation unprompted. • Language: You're committing quality code in any language your team needs OR you're best in class at one language • Mentoring: You have mentored several junior engineers around code quality | O23: • Quality: You're regularly trusted to lead complex and business-critical coding projects, including guiding others. • Documentation: Your code is consistently self-documenting where possible. You've regularly maintained, improved and extended existing documentation unprompted. • Language: You're committing quality code in any language your team needs OR you're best in class at one language • Mentoring: You have mentored several junior engineers around code quality | U23: • Quality: You're known as a hub of code knowledge across multiple teams, proposing and owning the implementation of new languages and technologies where appropriate • Documentation: You've organised documentation for large code projects efficiently, advising others on best practices where needed. • Language: You're best in class at your language of choice, and are committing quality code in other languages the organization needs. • Mentoring: You've actively mentored multiple senior engineers across the organization around code quality | AA23: • Quality: You've pushed the boundaries of the organization's coding practices, extending languages and libraries where needed. • Documentation: You've led efforts to improve documentation and code skills across the organization. You've actively pushed other engineers to improve how code is understood and read. • Language: You're contributing to the languages that your company uses, developing new patterns and paradigms to solve real business needs. • Mentoring: You're regularly mentoring mentors, raising the quality of every team member's code
A24: Testing | AG24: ✅ 5 / 3
A25: The ability to understand and implement great testing practices | C25: Understands how to test code, and the valuable role that testing plays | I25: Understands the importance of a testing strategy, with growing levels of autonomy | O25: Independently testing, advising the rest of the team on quality of tests | U25: A growing leader within the team around testing strategy | AA25: A leader within the organization in terms of test strategy | AH25: - item 1 - item 2 | AI25: - Q1 : TBD - Q2 : TBD
C26: • Testing your code: You consistently write solid unit tests, sometimes with help from more senior engineers • Improving coverage: You've spotted small areas of low test coverage and patched them • Taking responsibility You've consistently ensured that your code passes tests before creating or merging pull requests | I26: • Testing your code: You usually write detailed unit and functional tests covering edge cases as well as happy paths • Improving coverage: You've improved test coverage in adjacent areas of code to your own without being asked • Taking responsibility You've ensured that code committed by your immediate team is well tested and passing | O26: • Testing your code: You always write full tests for your code unassisted, covering all edge cases even with complex functionality. • Improving coverage: You've worked to improve the quality of your own and your team's test coverage • Taking responsibility You consistently look for and can recall quality metrics to demonstrate your test coverage, and monitor in behalf of your team. | U26: • Leading testing strategy: You've defined how your team writes and thinks through test coverage, including tooling and metrics. You've worked with other teams to ensure your strategy covers any crossover • Advocating for testing: You're an internal go-to expert when teams are thinking through testing strategy for new products and problems | AA26: • Leading testing strategy: You're defining how your company thinks through testing. You're personally responsibly for the metrics around test coverage across the organization • Advocating for testing: You may be contributing to an open source library or speaking at conferences on behalf of your company around great testing strategy and tactics
A27: Technical Understanding & Prioritisation | AG27: ✅ 5 / 3
A28: The ability to develop technical understanding and use this to prioritise tasks appropriately. | C28: Shows some confidence in technical understanding including the importance of prioritisation | I28: Is able to display a clear technical confidence and understanding, prioritises tasks and acts accordingly | O28: Is a technical and prioritisation leader within the team, including taking some ownership of other team members' technical growth and development. | U28: Is a technical and prioritisation leader across a set of related team's domains, consistently pushing boundaries and exploring gaps in understanding. | AA28: Is a technical and prioritisation leader across the organization's architecture consistently pushing boundaries and exploring gaps in understanding. | AH28: - item 1 - item 2 | AI28: - Q1 : TBD - Q2 : TBD
C29: • Understanding code: You are able to gain context within the team's domain with occasional help from more senior engineers. You are comfortable with the basics of code interface design and are learning to be more intentional • Technical collaboration: You communicate accurately about all technical subjects in your work. • Work breakdown: You understand the importance of rightsizing tasks for incremental delivery plus continuous integration. • Task prioritisation: You can plan work tasks with help from team members and manager. You deliver based on the agreed priority of works tasks. | I29: • Understanding code: You understand a good amount of the team's domain, and can gain sufficient context to work productively within that. • Technical collaboration: You can lead technical explanations when appropriate. You know when to listen and give space to team members. • Work breakdown: In advance of starting, you ensure that tasks are appropriately sized for incremental delivery and continuous integration, with some help from team members and your manager • Task prioritisation: You act according to task prioritisation whilst noting task dependencies | O29: • Understanding code: You understand your team's domain at a high level, including the breadth of services, how they interact, and data flows between systems. You understand adjacent domains as they affect your team • Technical collaboration: You actively facilitate technical discussions between team members and have a deep familiarity with technical topics under discussion • Work breakdown: You review projects critically, ensuring they are appropriately delineated and understood by the team • Task prioritisation: You ensure tasks are prioritised correctly, and that dependencies are noted and well understood by the team, including at the epic level. You foster a culture of priority setting and highlight the importance of alignment with organizational strategy | U29: • Understanding code: You have expertise in a set of related team's domains, including the breadth of services, how they interact, and data flows between systems. • Technical collaboration: You proactively seek out gaps in your technical understanding, and work with a variety of team members to fill those gaps. • Work breakdown: You critically review work across multiple teams, ensuring it is appropriately broken down, and well understood • Task prioritisation: You ensures cross-team dependencies are understood by all relevant stakeholders. You foster a culture of priority setting across teams and highlight the importance of alignment with organizational strategy | AA29: • Understanding code: You have expertise in the organization's architecture, including all domains, their bounded contexts, and how they interact with each other. • Technical collaboration: You have a deep technical understanding. You lead on helping team members fill gaps in their understanding. • Work breakdown: You critically review work across the organization, ensuring it is appropriately broken down. • Task prioritisation: You identify cross-organization dependencies and work with individual teams to resolve them. You lead on creating preventative measures to mitigate repeat occurrences. You foster a culture of priority setting across the organization driving the importance of alignment with organizational strategy
A30: Software Architecture | AG30: ✅ 5 / 3
A31: The ability to interact and engage with architectural approaches of the organization. | C31: Is able to design basic functions, avoiding duplication across codebases and interface-breaking changes based on an understanding of the overall service architecture | I31: Has a good understanding of, and designs functions that are aligned with, the overall service architecture | O31: Is able to consistently design code that is aligned with the overall service architecture. | U31: Regularly works across teams to build a culture for iterative, autonomous development and future scaling. | AA31: Regularly works across teams to build a culture for iterative, autonomous development and future scaling. | AH31: - item 1 - item 2 | AI31: - Q1 : TBD - Q2 : TBD
C32: • Reaction to feedback: You understand the feedback given and applies it consistently to your work. • Design: You are comfortable with the basics of code interface design, and are learning to be more intentional. • Technical debt: You can usually recognize technical debt and can pay it down when advised. | I32: • Design: You show a good intuition for code interface design. • Development: You consistently look for opportunities to learn from other projects and teams. • Technical debt: You consistently recognize technical debt and look for opportunities to negotiate and pay it down incrementally | O32: • Code: You are able to utilize abstractions and code isolation effectively. • Design: You have deep architectural and design pattern experience. You consult with team members only on more difficult designs. You set up new projects to ensure architectural success by anticipating future use cases and making design decisions that minimize the cost of future changes • Technical debt: You make plans with technical debt in mind, and how you will pay it down incrementally and consistently. You advise other team members on recognising and considering it | U32: • Design: You help several teams make design decisions that minimize the cost of future changes. • Development: You work with the architecture team to define cross- team architectural approaches. You sometimes employ prototyping for exploration of designs. • Technical debt: You understand technical debt as a long-term budgeting and risk management tool. You lead on when to incur more and when to pay it down. | AA32: • Design: You help several teams make design decisions that minimize the cost of future changes. • Development: You work with the architecture team to define cross- team architectural approaches. You sometimes employ prototyping for exploration of designs. • Technical debt: You understand technical debt as a long-term budgeting and risk management tool. You lead on when to incur more and when to pay it down.
A33: Security | AG33: ✅ 5 / 3
A34: The ability to understand and apply security principles, handle user data appropriately and report security concerns | C34: Is able to understand the importance of security. | I34: Is able to understand the importance of security and starts to see work through a security lens. | O34: Consistently approaches all engineering work with a security lens. | U34: Consistently promotes a security first mindset within the team, leading by example. | AA34: Is a leader in security strategy. | AH34: - item 1 - item 2 | AI34: - Q1 : TBD - Q2 : TBD
C35: • Knowledge: You understand basic security principles and apply them to your daily work. • User data: You understand the importance of handling user data and do so responsibly. • Reporting: You immediately report security concerns to manager or security teams. | I35: • Knowledge: You understand general security principles and apply them to your daily work. You ask more senior engineers for help on making decisions that may have security implications. • User data: You understand the importance of handling user data and does so responsibly without exception. • Reporting: You immediately reports security concerns to manager or security teams. | O35: • Knowledge: You have an excellent understanding of security principles and you work to better facilitate the team's understanding. • User data: You have faultless handling of user data, and set an example for others within the team. • Proactivity: You actively look for security vulnerabilities both in the code and when providing peer reviews. • Collaboration: You work with the security teams to help refine technical strategy. | U35: • Knowledge: You have impeccable understanding of security principles, and regularly impart this knowledge on your team. • User data: You have faultless handling of user data, setting an example within the organization. • Strategy: You lead on collaboration between your team and the security teams, to refine the team's approach to security based on the organization's security strategy. You contribute to the organization's broader security strategy. | AA35: • Knowledge: You have impeccable understanding of security principles, and impart this knowledge on your own team, the organization, and wider tech community. • Strategy: You lead the conversation around security within the organization. You are seen as an expert in the security field.
A36: Debugging & Monitoring | AG36: ✅ 5 / 3
A37: The ability to understand and implement systematic debugging and monitoring practices to diagnose issues | C37: Understands debugging basics, the appropriate tools to use and is beginning to implement good monitoring practices | I37: Understands debugging basics, the appropriate tools to use and is beginning to implement good monitoring practices | O37: Uses systematic debugging to diagnose all issues located to a single service and drives monitoring work across the team | U37: Uses systematic debugging to diagnose all issues within a set of related domains and leads in fostering a culture of observability and monitoring across several teams | AA37: Leads incident response, and fosters and promotes a culture of observability and monitoring across the organization. | AH37: - item 1 - item 2 | AI37: - Q1 : TBD - Q2 : TBD
C38: • Debugging: You are able do basic code profiling and optimize obvious bugs • Tools: You use out-of-the box tools to instrument and monitor systems with occasional help from senior engineers. • Philosophy: You understand the team's monitoring philosophy and work comfortably within it. | I38: • Debugging: You can do multi application and multi layer profiling without support and optimize almost all bugs • Tools: You customize out of the box tools, and on occasion create small custom tools to instrument and monitor systems. • Philosophy: You understand the organization's monitoring philosophy. You help tune and change the monitoring philosophy on your team. • Data: You understand the operational data for your team's domain. | O38: • Debugging: You use systematic debugging to diagnose cross service issues, sometimes with help from more senior engineers. • Tools: You can judge whether a new tool is necessary to instrument and monitor systems. You can create that tool if required. • Philosophy: You understand the cross-functional and cross-organization implications of your team's monitoring philosophy. You proactively seek to refine the monitoring philosophy of your team. • Data: You are aware of the operational data for your team and use it as a basis for driving changes to your team's services to achieve stability and performance improvements. • Mentoring: You act as a primary mentor for the rest of their team on running systems. | U38: • Debugging: You use systematic debugging to diagnose cross service issues • Philosphy: You drive monitoring work across several teams based on the organization's monitoring philosophy. • Data: You are aware of the operational data for domains of several teams and use it to drive changes to the teams' services to achieve stability and performance improvements. • Profiling: You can solve any profiling challenge at any layer of the stack. • Mentoring: You actively seek to mentor any junior engineer or manager on running systems. | AA38: • Debugging: Uses systematic debugging to diagnose issues across the organization. • Philosophy: You lead the organization's monitoring philosophy. • Data: You teams across the organization use operational data to improve stability and performance of their domains. • Mentoring: You are a mentor for senior managers across the organization.
A40: LEADERSHIP
A41: Hiring and Org Design | AG41: ✅ 5 / 3
A42: The ability to understand the needs of the business and ensure that your team can meet them | I42: A competent interviewer. Able to follow a structured hiring process, and make a decision. | O42: A competent interviewer. Able to follow a structured hiring process, and make a decision. | U42: A competent interviewer. Able to follow a structured hiring process, and make a decision. | AA42: A competent interviewer. Able to follow a structured hiring process, and make a decision. | AH42: - item 1 - item 2 | AI42: - Q1 : TBD - Q2 : TBD
I43: • Deploying Teams: You've carved out an additional role for yourself or peers to fulfil a need that a team has. • Employer Brand: You've helped to establish the company as a good employer through promotion on stage or online. You've inputted into the company's careers pages. • Hiring: You are regularly part of hiring panels, and have been hiring manager for at least one hire that passed probation. | O43: • Deploying Teams: You've carved out an additional role for yourself or peers to fulfil a need that a team has. • Employer Brand: You've helped to establish the company as a good employer through promotion on stage or online. You've inputted into the company's careers pages. • Hiring: You are regularly part of hiring panels, and have been hiring manager for at least one hire that passed probation. | U43: • Deploying Teams: You've carved out an additional role for yourself or peers to fulfil a need that a team has. • Employer Brand: You've helped to establish the company as a good employer through promotion on stage or online. You've inputted into the company's careers pages. • Hiring: You are regularly part of hiring panels, and have been hiring manager for at least one hire that passed probation. | AA43: • Deploying Teams: You've carved out an additional role for yourself or peers to fulfil a need that a team has. • Employer Brand: You've helped to establish the company as a good employer through promotion on stage or online. You've inputted into the company's careers pages. • Hiring: You are regularly part of hiring panels, and have been hiring manager for at least one hire that passed probation.
A44: Stakeholder Management | AG44: ✅ 5 / 3
A45: The ability to ensure that teams are protected and expectations are set correctly | C45: Is able to keep tangential teams informed and expectations managed around everyday work updates. Uses judgement about others' reaction when disclosing information and opinions. | I45: Known for being efficient and reliable, and doing what they say they will do. Proactively managed expectations even when it results in frustration or personal reputation risk. | O45: Is able to proactively inform stakeholders both within and outside the organisation with pertinent and timely information, including bad news. Able to read and adapt to personalities across the organisation. Has good relationships with all key stakeholders. | U45: An expert at understanding everyone's motivations and drives, and adapting communication and priorities to fit them. Protects others, including when it results in hard conversations. Maintains good relationships with all key stakeholders even when challenging. | AA45: An expert at understanding everyone's motivations and drives, and adapting communication and priorities to fit them. Protects others, including when it results in hard conversations. Maintains good relationships with all key stakeholders even when challenging. | AH45: - item 1 - item 2 | AI45: - Q1 : TBD - Q2 : TBD
C46: • Managing Goals and Expectations: You lead on successful projects with external clients, internal stakeholders or partners with a successful outcome, ensuring goals are understood throughout. • Foresight: You work to inform departments, stakeholders or clients of an issue they face without being asked or expected to do so. • Engendering Trust: You bring stakeholders or clients into a process in a way that makes best use of their time and their strengths. • Protecting the Team: You manage a client or stakeholder relationship for a project. | I46: • Managing Goals and Expectations: You lead multiple smaller projects with external clients or internal stakeholders, with a successful outcome. • Foresight: You anticipate issues or requirements on projects in advance and work to raise those with key people outside your team. This has resulted in noticeable efficiency gains. • Engendering Trust: You run several small to medium sized projects in a leadership capacity, working closely with clients and stakeholders with positive reviews. • Protecting the Team: You create space for others in your team to do their best work by managing client or stakeholder relationships. | O46: • Managing Goals and Expectations: You lead multiple larger projects with external clients or internal stakeholders, including managing bad news and scope creep or timeline slippage, with successful outcomes. • Foresight: You look for misalignment across large scopes of work involving multiple clients or stakeholders, and ensure that they're smoothed out in advance. • Engendering Trust: You've repeatedly proven yourself able to work closely with clients or stakeholders in ways that earn respect and results. You use their time wisely and lean into their knowledge. • Protecting the Team: You protect direct reports from difficult stakeholders across multiple projects. | U46: • Managing Goals and Expectations: You lead entire client or stakeholder relationships over the course of multiple quarters across successful and unsuccessful projects whilst maintaining good outcomes. • Foresight: Your foresight has been proven over multiple projects involving multiple teams. You act as the stakeholder or client in order to tease out extra requirements, due to your deep understanding of their incentives. • Engendering Trust: You're a key contact for stakeholders or external clients, funnelling work and information to them as you see fit. They ask for you to be involved in processes and meetings due to your respect for their time and needs. • Protecting the Team: You protect embattled teams from being thrown off course, identifying difficult clients and stakeholder roadblocks, resolving issues. | AA46: • Managing Goals and Expectations: You lead entire client or stakeholder relationships over the course of multiple quarters across successful and unsuccessful projects whilst maintaining good outcomes. • Foresight: Your foresight has been proven over multiple projects involving multiple teams. You act as the stakeholder or client in order to tease out extra requirements, due to your deep understanding of their incentives. • Engendering Trust: You're a key contact for stakeholders or external clients, funnelling work and information to them as you see fit. They ask for you to be involved in processes and meetings due to your respect for their time and needs. • Protecting the Team: You protect embattled teams from being thrown off course, identifying difficult clients and stakeholder roadblocks, resolving issues.
A47: Team Leadership | AG47: ✅ 5 / 3
A48: The ability to maintain quality, efficiency and establish trust in your ability | O48: Capable of informally managing interns, contractors, suppliers and agencies. Possibly manages one or two junior team members. Doesn't look for glory, and doesn't complain about boring work. Assumes good decisions in others work. Broadly does what they say they're going to do. | U48: Capable of managing a small team effectively. Happily sits in meetings so the team doesn't have to. Follows through on promises around work, rewards and time. | AA48: Capable of managing a larger team effectively. Protects the team, ensuring they're always clear on the goal, but also works to create space for them to make decisions and grow. Zero ego: open and honest with intentions, goals, failings and expectations. Dependable to a fault, leading to deep trust amongst direct reports. | AH48: - item 1 - item 2 | AI48: - Q1 : TBD - Q2 : TBD
O49: • Putting the Team first: You regularly make time for listening to and understanding the people you're responsible for. • Difficult Conversations: You have helped someone on your team out with a difficult personal decision and acted in an objective, professional manner. • Reliability: You have been open about your intentions when making a team-level decision – for example moving people between teams or introducing new role expectations – and followed through. • Vulnerability: You have proactively admitted fault and weakness in yourself to team members, and admitted a mistake made in work you've done. | U49: • Putting the Team first: You put the team first in your priority list, as demonstrated by several examples of you taking on administrative or boring work on their behalf. • Difficult Conversations: You have had hard conversations about compensation, performance or work-related issues with members of your team, and dealt with them effectively and professionally • Reliability: You have been consistently open about intentions and reliable when executing multiple team-level decisions affecting the working days and potential happiness of your team. • Vulnerability: You share your strengths and development areas with your team regularly, encouraging feedback and support. You own up whenever you've failed and apologise when appropriate. | AA49: • Putting the Team first: You're visibly selfless and devoted as a manager. You have repeatedly put the team first in decisions which affect your workload. You've given opportunities for your team to shine in situations you could have taken yourself. • Difficult Conversations: You have, over a significant period of time, managed team-level conversations effectively, as proven by your ability to maintain a largely happy and committed team throughout your tenure. • Reliability: You have been honest and open about intentions and goals with regards to at least one major team level decisions affecting multiple direct reports. You've listened to feedback and adjusted plans where possible. You have delivered as promised. • Vulnerability: You make a point of asking for feedback on your actions from your team. You consciously make time for self-reflection and evaluation, which you open up for others to view. You recognise the value of being human to your team.
A50: Developing Others | AG50: ✅ 5 / 3
A51: The ability to develop the skillsets and abilities of your team | O51: Able to recognise the strengths of peers, and look for ways to support those strengths through project work. Has invested time in materials or process to support team growth. Peers see them as an informal coach. | U51: Actively looking for and honing in on the strengths of direct reports, and finding ways to up-skill them. Regularly digging into motivations and ambitions of the team, and building goals and process around them. As a result, team members visibly grow and progress over time. | AA51: Has a structured process and methodology for assessing, refining and supporting the strengths and goals of their team. Spends meaningful time investing in laying groundwork for personal growth, including milestones, goals and structured opportunities. Their team are growing at above average speed. | AH51: - item 1 - item 2 | AI51: - Q1 : TBD - Q2 : TBD
O52: • Identifying strengths: You recognise natural strengths in your peers which you help them to nurture. • Supporting team growth: You support and champion peers in their personal growth, celebrating a promotion, successful project or praise from others. • Investing in process: You invest in your future through a process of skills assessment to define your future direction. • Feedback on work: Your feedback to peers on their work is honest, actionable and timely. You put the needs of the project over personal inhibitions. You're comfortable with having your mind changed. | U52: • Identifying strengths: You seek out and identify natural strength in your team, which you turn into goals. This results in measurable improvements in at least one report's skillset. • Supporting team growth: You support multiple reports in their personal growth, giving them opportunities to train and rewarding them when complete. You follow through on promises you set around progression through your organisation. • Investing in process: You invest in your team's development through assessment and growth-tracking, which has results in measurable completed goals. • Feedback on work: Your feedback on your team's work is honest, actionable and timely. You ask what level they need feedback on and ensure you stick to that level. You don't give feedback when you don't have enough context to be useful, and expect to be wrong a significant amount of the time. | AA52: • Identifying strengths: You find threads of passion or strength across a large team, and help team members to grow those strengths. • Supporting team growth: You set growth targets for your team, and are clear on what is expected and how they'll be rewarded upon completion. You follow through on that promise. You establish budgets and space for active learning. • Investing in process: You invest in rigorous and standardised skills assessment and goal-setting for your team, introducing clarity and purpose, resulting in your team growing in a more focused direction. • Feedback on work: Your feedback on multiple teams' work is strictly useful and actionable. You're able to articulate in a fair and efficient way not only what your opinion is, but why you have that opinion. In disagreement you're comfortable with having your opinion changed and invite other opinions from those around you.
A53: Culture & Togetherness | AG53: ✅ 5 / 3
A54: The ability to bring groups together and foster a happy and productive environment | C54: Actively signals according to behaviour they want to see. Keeps a cool head around others even in stressful situations. Is involved in the planning and organising of team activities. | I54: Actively signals according to behaviour they want to see. Keeps a cool head around others even in stressful situations. Is involved in the planning and organising of team activities. | O54: Works to build and document behaviours they expect to see. Has trusted relationships with both junior colleagues and peers, and can describe where the organisation is strong or needs development. Organises regular team activities. | U54: Has built themselves into an important cultural guardian through both signalling and empowering others. Goes out of their way to promote good behaviour and safeness for all. Is sharing the team's culture and wellbeing outwardly | AA54: Has built themselves into an important cultural guardian through both signalling and empowering others. Goes out of their way to promote good behaviour and safeness for all. Is sharing the team's culture and wellbeing outwardly | AH54: - item 1 - item 2 | AI54: - Q1 : TBD - Q2 : TBD
C55: • Setting an Example: You state your expectations of how your team should work and act, then demonstrate those expectations yourself. You ask for feedback on your signalling and make a changes where appropriate. • Encouraging diverse opinions: You help to organise and activate efforts towards a fairer, more diverse and safer workplace. • Developing personal relationships: You invest in the relationships you are fostering with your team. You respect the sanctity of pastoral care and 1:1 time. You don't cancel and are never late. | I55: • Setting an Example: You state your expectations of how your team should work and act, then demonstrate those expectations yourself. You ask for feedback on your signalling and make a changes where appropriate. • Encouraging diverse opinions: You help to organise and activate efforts towards a fairer, more diverse and safer workplace. • Developing personal relationships: You invest in the relationships you are fostering with your team. You respect the sanctity of pastoral care and 1:1 time. You don't cancel and are never late. | O55: • Setting an Example: You make an effort to document a cultural charter for your team, which you cite regularly and stick to rigorously. If you break your rules, you expect to be called out. • Encouraging diverse opinions: You're leading efforts to improve diversity in your everyday environment, organising working groups, events and discussion across large parts of your organisation. • Developing personal relationships: You make a point of knowing all about the people who report directly to you. You build close yet professional relationships with all direct reports fostering good levels of trust. | U55: • Setting an Example: You actively call out peers and seniors who you feel don't signal correctly to your team and yourself. You work to educate those in positions of power to be conscious of the example they're setting. • Encouraging diverse opinions: You're a core part of, or leading, a central initiative towards a fairer and safer workplace for all, including touching hiring strategy and coaching for key staff. You're a vocal champion for under-represented groups. You create safe spaces for debate. • Developing personal relationships: You're close enough to both your reports and your peers to be able to spot and debug issues with culture early and often. You can predict how people will work together and interact because you know their viewpoints on the world. You're coaching other leaders in their 1:1 and interpersonal techniques. | AA55: • Setting an Example: You actively call out peers and seniors who you feel don't signal correctly to your team and yourself. You work to educate those in positions of power to be conscious of the example they're setting. • Encouraging diverse opinions: You're a core part of, or leading, a central initiative towards a fairer and safer workplace for all, including touching hiring strategy and coaching for key staff. You're a vocal champion for under-represented groups. You create safe spaces for debate. • Developing personal relationships: You're close enough to both your reports and your peers to be able to spot and debug issues with culture early and often. You can predict how people will work together and interact because you know their viewpoints on the world. You're coaching other leaders in their 1:1 and interpersonal techniques.
